{"_format_sort_fields": ["quality", "res", "fps", "hdr:12", "source", "vcodec", "channels", "acodec", "lang", "proto"], "_type": "video", "_version": {"release_git_head": "197d0b03b6a3c8fe4fa5ace630eeffec629bf72c", "repository": "yt-dlp/yt-dlp", "version": "2024.11.04"}, "abr": 139.669, "acodec": "opus", "age_limit": 0, "aspect_ratio": 0.56, "asr": 48000, "audio_channels": 2, "availability": "public", "categories": ["Gaming"], "channel": "Takanashi Kiara Ch. hololive-EN", "channel_follower_count": 1550000, "channel_id": "UCHsx4Hqa-1ORjQTh9TYDhww", "channel_is_verified": true, "channel_url": "https://www.youtube.com/channel/UCHsx4Hqa-1ORjQTh9TYDhww", "comment_count": 308, "description": "Based On The\nOriginal Song by: Lappy\nOriginal MV by: @chinjireta\n\nArt and Video: @Dakuma_Art\n\n--------------------------------\nRequest from hololive production to underage viewers\nPlease search for [Request To Minors] or click on the link below, to read it and enjoy the video\nhttps://hololivepro.com/en/request-to-minors/\n-------------------------------", "display_id": "TpHa-WorKtQ", "duration": 25, "duration_string": "25", "dynamic_range": "SDR", "epoch": 1732750649, "ext": "webm", "extractor": "youtube", "extractor_key": "Youtube", "filesize_approx": 7618321, "format": "248 - 1080x1920 (1080p)+251 - audio only (medium)", "format_id": "248+251", "format_note": "1080p+medium", "fps": 30, "fulltitle": "WAWA BOOTY SHORTS \ud83d\ude33\u2728\ufe0f #shorts", "height": 1920, "id": "TpHa-WorKtQ", "is_live": false, "language": "ko", "like_count": 10445, "live_status": "not_live", "playable_in_embed": true, "protocol": "https+https", "resolution": "1080x1920", "tags": [], "tbr": 2488.3579999999997, "thumbnail": "https://i.ytimg.com/vi/TpHa-WorKtQ/hq720_2.jpg?sqp=-oaymwE2CK4FEIIDSEbyq4qpAygIARUAAIhCGABwAcABBvABAfgBtgiAAoAPigIMCAAQARh_IDsoLjAP&rs=AOn4CLDjCncyIKLQzS8Wmnid8WG3rUbkfA", "timestamp": 1719844603, "title": "WAWA BOOTY SHORTS \ud83d\ude33\u2728\ufe0f #shorts", "upload_date": "20240701", "uploader": "Takanashi Kiara Ch. hololive-EN", "uploader_id": "@TakanashiKiara", "uploader_url": "https://www.youtube.com/@TakanashiKiara", "vbr": 2348.689, "vcodec": "vp09.00.40.08", "view_count": 81240, "was_live": false, "webpage_url": "https://www.youtube.com/watch?v=TpHa-WorKtQ", "webpage_url_basename": "watch", "webpage_url_domain": "youtube.com", "width": 1080}