{"_format_sort_fields": ["quality", "res", "fps", "hdr:12", "source", "vcodec", "channels", "acodec", "lang", "proto"], "_type": "video", "_version": {"release_git_head": "197d0b03b6a3c8fe4fa5ace630eeffec629bf72c", "repository": "yt-dlp/yt-dlp", "version": "2024.11.04"}, "abr": 126.757, "acodec": "opus", "age_limit": 0, "aspect_ratio": 1.78, "asr": 48000, "audio_channels": 2, "availability": "public", "categories": ["Entertainment"], "channel": "hololive English", "channel_follower_count": 797000, "channel_id": "UCotXwY6s8pWmuWd_snKYjhg", "channel_url": "https://www.youtube.com/channel/UCotXwY6s8pWmuWd_snKYjhg", "comment_count": 1400, "description": "hololive English Eurobeat Remix Album Merchandise now available!\n\n\u25bcOfficial Online Shop\u25bc\nJP: https://shop.hololivepro.com/products/hololiveen_eurobeat2024\nEN: https://shop.hololivepro.com/en/products/hololiveen_eurobeat2024\n\n\u25bcGeek Jack\u25bc\nEN: https://shop.geekjack.net/collections/hololive-english\nCH: https://shop.geekjack.net/zh/collections/hololive-english\n\nhololive English Eurobeat Remix Album, available from October 26th, 12AM local time!\nStreaming: https://cover.lnk.to/3dcIzh\n\n#holoEN \n\n\u25c6Credits\nEurobeat Remixes and Arrangements: @TurboA \nIllustrations: https://x.com/lienliensn\nGIF Animations: https://x.com/SeterMD\n\nFollow the members of hololive English!\n\n\u25b6Mori Calliope\n@MoriCalliope \nhttps://twitter.com/moricalliope\n\n\u25b6Hakos Baelz\n@HakosBaelz \nhttps://twitter.com/hakosbaelz\n\n\u25b6Fuwawa Abyssgard & Mococo Abyssgard (FUWAMOCO)\n@FUWAMOCOch \nhttps://twitter.com/fuwamoco_en\n\n\u25b6Ouro Kronii\n@OuroKronii \nhttps://twitter.com/ourokronii\n\n\u25b6Takanashi Kiara\n@TakanashiKiara \nhttps://twitter.com/takanashikiara\n\n\u25b6IRyS\n@IRyS \nhttps://twitter.com/irys_en\n\n\u25b6Nanashi Mumei\n@NanashiMumei \nhttps://twitter.com/nanashimumei_en\n\n\u25b6Ninomae Ina'nis\n@NinomaeInanis \nhttps://twitter.com/ninomaeinanis\n\n\u25b6Ceres Fauna\n@CeresFauna \nhttps://twitter.com/ceresfauna\n\n\u25b6Koseki Bijou\n@KosekiBijou \nhttps://twitter.com/kosekibijou\n\n\u25b6Watson Amelia\n@WatsonAmelia \nhttps://twitter.com/watsonameliaEN\n\n\u25b6Nerissa Ravencroft\n@NerissaRavencroft \nhttps://twitter.com/nerissa_en\n\n\u25b6Elizabeth Rose Bloodflame\n@holoen_erbloodflame \nhttps://twitter.com/ERBloodflame\n\n\u25b6Gigi Murin\n@holoen_gigimurin \nhttps://twitter.com/gigimurin\n\n\u25b6Cecilia Immergreen\n@holoen_ceciliaimmergreen \nhttps://twitter.com/ceciliaimgreen\n\n\u25b6Raora Panthera\n@holoen_raorapanthera \nhttps://twitter.com/raorapanthera\n\n\u25b6Request from hololive production to underage viewers\nPlease search for [Request To Minors] or click on the link below, to read it and enjoy the video\nhttps://hololivepro.com/en/request-to-minors/", "display_id": "w_WIIMlVIzw", "duration": 3312, "duration_string": "55:12", "dynamic_range": "SDR", "epoch": 1732750821, "ext": "webm", "extractor": "youtube", "extractor_key": "Youtube", "filesize_approx": 52475852, "format": "616 - 1920x1080 (Premium)+251 - audio only (medium)", "format_id": "616+251", "format_note": "Premium+medium", "fps": 30.0, "fulltitle": "\u3010MV\u3011hololive English Eurobeat Remix Album", "height": 1080, "id": "w_WIIMlVIzw", "is_live": false, "language": "en", "like_count": 42925, "live_status": "not_live", "playable_in_embed": true, "protocol": "m3u8_native+https", "release_date": "20241025", "release_timestamp": 1729825926, "release_year": 2024, "resolution": "1920x1080", "tags": [], "tbr": 5816.125999999999, "thumbnail": "https://i.ytimg.com/vi/w_WIIMlVIzw/maxresdefault.jpg", "timestamp": 1729825926, "title": "\u3010MV\u3011hololive English Eurobeat Remix Album", "upload_date": "20241025", "uploader": "hololive English", "uploader_id": "@hololiveEnglish", "uploader_url": "https://www.youtube.com/@hololiveEnglish", "vbr": 5689.369, "vcodec": "vp09.00.40.08", "view_count": 535752, "was_live": false, "webpage_url": "https://www.youtube.com/watch?v=w_WIIMlVIzw", "webpage_url_basename": "watch", "webpage_url_domain": "youtube.com", "width": 1920}