{"_format_sort_fields": ["quality", "res", "fps", "hdr:12", "source", "vcodec", "channels", "acodec", "lang", "proto"], "_type": "video", "_version": {"release_git_head": "54216696261bc07cacd9a837c501d9e0b7fed09e", "repository": "yt-dlp/yt-dlp", "version": "2024.12.13"}, "abr": 30.783, "acodec": "mp4a.40.5", "age_limit": 0, "asr": 22050, "audio_channels": 2, "audio_ext": "m4a", "automatic_captions": {}, "availability": "public", "categories": ["Music"], "channel": "hololive \u30db\u30ed\u30e9\u30a4\u30d6 - VTuber Group", "channel_follower_count": 2660000, "channel_id": "UCJFZiqLMntJufDCHc6bQixg", "channel_is_verified": true, "channel_url": "https://www.youtube.com/channel/UCJFZiqLMntJufDCHc6bQixg", "comment_count": 618, "container": "m4a_dash", "description": "\u3010hololive 5th fes. Capture the Moment Supported By BUSHIROAD\u3011\n\u516c\u6f14\u306e\u4e00\u90e8\u3092YouTube Live\u3067\u7121\u6599\u914d\u4fe1\uff01\n\u5168\u7de8\u3092\u3054\u89a7\u306b\u306a\u308a\u305f\u3044\u65b9\u306f\u4e0b\u8a18\u3088\u308a\u30c1\u30b1\u30c3\u30c8\u3092\u3054\u8cfc\u5165\u304f\u3060\u3055\u3044\u3002\n\u30cf\u30c3\u30b7\u30e5\u30bf\u30b0\u300c #hololivefesEXPO24_DAY1\u300d\u3067\u5fdc\u63f4\u3057\u3066\u304f\u3060\u3055\u3044\uff01\n\n\u25bc\u672c\u7de8\u30c1\u30b1\u30c3\u30c8\u8cfc\u5165(Purchase streaming tickets)\n\u65e5\u672c : https://hololivesuperexpo2024.hololivepro.com/tickets\nOverseas : https://hololivesuperexpo2024.hololivepro.com/en/tickets\n\u203b\u914d\u4fe1\u30c1\u30b1\u30c3\u30c8\u306f2024\u5e744\u670817\u65e5\uff08\u6c34\uff09 23:59\u307e\u3067\u8ca9\u58f2\u3057\u3066\u304a\u308a\u3001\u30a2\u30fc\u30ab\u30a4\u30d6\u306f2024\u5e744\u670818\u65e5\uff08\u6728\uff09 23:59\u307e\u3067\u4f55\u5ea6\u3067\u3082\u8996\u8074\u3067\u304d\u307e\u3059\u3002\n\n\u25bcGOODS \u901a\u8ca9\u8cfc\u5165(Purchase merchandises via mail order)\n\u65e5\u672c\uff1a https://hololivesuperexpo2024.hololivepro.com/merch\nOverseas\uff1a https://hololivesuperexpo2024.hololivepro.com/en/merch\n\n\u25bc\u516c\u5f0f\u30cf\u30c3\u30b7\u30e5\u30bf\u30b0\uff08EXPO\u30fbfes.\u5171\u901a\uff09\n#hololivefesEXPO24_DAY1\n\n\u25bc\u30a4\u30d9\u30f3\u30c8\u7279\u8a2dHP( #hololivefesEXPO24 Official HP)\nhttps://hololivesuperexpo2024.hololivepro.com/fes\n\u25b7\u30db\u30ed\u30e9\u30a4\u30d6\u516c\u5f0f\u30b5\u30a4\u30c8\uff1ahttps://hololive.hololivepro.com/\n\u25b7\u30db\u30ed\u30e9\u30a4\u30d6\u30d7\u30ed\u30c0\u30af\u30b7\u30e7\u30f3\u516c\u5f0fTwitter\uff1a https://twitter.com/hololivetv\n\u25b7\u914d\u4fe1\u30b9\u30b1\u30b8\u30e5\u30fc\u30eb\uff1ahttps://schedule.hololive.tv/\n\n\u25b6\u914d\u4fe1\u3092\u697d\u3057\u3093\u3067\u3044\u305f\u3060\u304f\u305f\u3081\u306e\u304a\u9858\u3044/Rule\u25b7\n\u30fb\u5f85\u6a5f\u6240\u3084\u30b3\u30e1\u30f3\u30c8\u6b04\u306f\u3001\u304a\u4e92\u3044\u30de\u30ca\u30fc\u3092\u5b88\u3063\u3066\u3054\u5229\u7528\u304f\u3060\u3055\u3044\u3002\n\u30fb\u30b3\u30e1\u30f3\u30c8\u3084\u30b9\u30fc\u30d1\u30fc\u30c1\u30e3\u30c3\u30c8\u304c\u30aa\u30f3\u306e\u6642\u306f\u3001\u4ed6\u306e\u65b9\u306e\u3054\u8ff7\u60d1\u306b\u306a\u308b\u8a00\u52d5\u306f\u3054\u9060\u616e\u304f\u3060\u3055\u3044\u3002\u307e\u305f\u3001\u305d\u306e\u3088\u3046\u306a\u8a00\u52d5\u306b\u5bfe\u3057\u3066\u53cd\u5fdc\u3059\u308b\u3053\u3068\u3082\u304a\u63a7\u3048\u304f\u3060\u3055\u3044\u3002\n- Please be respectful to others in stream waiting rooms and live chat.\n- When comments or Super Chats are enabled, please refrain from sending inappropriate messages or responding to such messages.\n\n-----\n\u203b\u30db\u30ed\u30e9\u30a4\u30d6\u30d7\u30ed\u30c0\u30af\u30b7\u30e7\u30f3\u304b\u3089\u672a\u6210\u5e74\u306e\u8996\u8074\u8005\u306e\u65b9\u3005\u3078\u306e\u304a\u9858\u3044\n\u4e0b\u8a18\u30ea\u30f3\u30af\u3092\u3054\u78ba\u8a8d\u306e\u4e0a\u3001\u304a\u697d\u3057\u307f\u304f\u3060\u3055\u3044\u3002\nhttps://www.hololive.tv/request-to-minors", "display_id": "00xeNL3vdQo", "downloader_options": {"http_chunk_size": 10485760}, "duration": 6115, "duration_string": "1:41:55", "epoch": 1735062696, "ext": "m4a", "extractor": "youtube", "extractor_key": "Youtube", "filesize": 23530782, "filesize_approx": 23530371, "format": "599 - audio only (ultralow)", "format_id": "599", "format_note": "ultralow", "formats": [{"abr": 0, "acodec": "none", "aspect_ratio": 1.78, "audio_ext": "none", "columns": 10, "ext": "mhtml", "format": "sb3 - 48x27 (storyboard)", "format_id": "sb3", "format_note": "storyboard", "fps": 0.016353229762878167, "fragments": [{"duration": 6115.0, "url": "https://i.ytimg.com/sb/00xeNL3vdQo/storyboard3_L0/default.jpg?sqp=-oaymwENSDfyq4qpAwVwAcABBqLzl_8DBgi7ydSvBg==&sigh=rs$AOn4CLCbJurUGTH4tgtdb9sN7EYXHCqZ0Q"}], "height": 27, "http_headers": {"Accept": "text/html,application/xhtml+xml,application/xml;q=0.9,*/*;q=0.8", "Accept-Language": "en-us,en;q=0.5", "Sec-Fetch-Mode": "navigate", "User-Agent": "Mozilla/5.0 (Windows NT 10.0; Win64; x64) AppleWebKit/537.36 (KHTML, like Gecko) Chrome/92.0.4515.159 Safari/537.36"}, "protocol": "mhtml", "resolution": "48x27", "rows": 10, "url": "https://i.ytimg.com/sb/00xeNL3vdQo/storyboard3_L0/default.jpg?sqp=-oaymwENSDfyq4qpAwVwAcABBqLzl_8DBgi7ydSvBg==&sigh=rs$AOn4CLCbJurUGTH4tgtdb9sN7EYXHCqZ0Q", "vbr": 0, "vcodec": "none", "video_ext": "none", "width": 48}, {"abr": 0, "acodec": "none", "aspect_ratio": 1.78, "audio_ext": "none", "columns": 10, "ext": "mhtml", "format": "sb2 - 80x45 (storyboard)", "format_id": "sb2", "format_note": "storyboard", "fps": 0.10024529844644317, "fragments": [{"duration": 997.5530179445351, "url": "https://i.ytimg.com/sb/00xeNL3vdQo/storyboard3_L1/M0.jpg?sqp=-oaymwENSDfyq4qpAwVwAcABBqLzl_8DBgi7ydSvBg==&sigh=rs$AOn4CLBCUN1woq0sTrP0YSVCdwu-MSR8PA"}, {"duration": 997.5530179445351, "url": "https://i.ytimg.com/sb/00xeNL3vdQo/storyboard3_L1/M1.jpg?sqp=-oaymwENSDfyq4qpAwVwAcABBqLzl_8DBgi7ydSvBg==&sigh=rs$AOn4CLBCUN1woq0sTrP0YSVCdwu-MSR8PA"}, {"duration": 997.5530179445351, "url": "https://i.ytimg.com/sb/00xeNL3vdQo/storyboard3_L1/M2.jpg?sqp=-oaymwENSDfyq4qpAwVwAcABBqLzl_8DBgi7ydSvBg==&sigh=rs$AOn4CLBCUN1woq0sTrP0YSVCdwu-MSR8PA"}, {"duration": 997.5530179445351, "url": "https://i.ytimg.com/sb/00xeNL3vdQo/storyboard3_L1/M3.jpg?sqp=-oaymwENSDfyq4qpAwVwAcABBqLzl_8DBgi7ydSvBg==&sigh=rs$AOn4CLBCUN1woq0sTrP0YSVCdwu-MSR8PA"}, {"duration": 997.5530179445351, "url": "https://i.ytimg.com/sb/00xeNL3vdQo/storyboard3_L1/M4.jpg?sqp=-oaymwENSDfyq4qpAwVwAcABBqLzl_8DBgi7ydSvBg==&sigh=rs$AOn4CLBCUN1woq0sTrP0YSVCdwu-MSR8PA"}, {"duration": 997.5530179445351, "url": "https://i.ytimg.com/sb/00xeNL3vdQo/storyboard3_L1/M5.jpg?sqp=-oaymwENSDfyq4qpAwVwAcABBqLzl_8DBgi7ydSvBg==&sigh=rs$AOn4CLBCUN1woq0sTrP0YSVCdwu-MSR8PA"}, {"duration": 129.68189233278918, "url": "https://i.ytimg.com/sb/00xeNL3vdQo/storyboard3_L1/M6.jpg?sqp=-oaymwENSDfyq4qpAwVwAcABBqLzl_8DBgi7ydSvBg==&sigh=rs$AOn4CLBCUN1woq0sTrP0YSVCdwu-MSR8PA"}], "height": 45, "http_headers": {"Accept": "text/html,application/xhtml+xml,application/xml;q=0.9,*/*;q=0.8", "Accept-Language": "en-us,en;q=0.5", "Sec-Fetch-Mode": "navigate", "User-Agent": "Mozilla/5.0 (Windows NT 10.0; Win64; x64) AppleWebKit/537.36 (KHTML, like Gecko) Chrome/92.0.4515.159 Safari/537.36"}, "protocol": "mhtml", "resolution": "80x45", "rows": 10, "url": "https://i.ytimg.com/sb/00xeNL3vdQo/storyboard3_L1/M$M.jpg?sqp=-oaymwENSDfyq4qpAwVwAcABBqLzl_8DBgi7ydSvBg==&sigh=rs$AOn4CLBCUN1woq0sTrP0YSVCdwu-MSR8PA", "vbr": 0, "vcodec": "none", "video_ext": "none", "width": 80}, {"abr": 0, "acodec": "none", "aspect_ratio": 1.78, "audio_ext": "none", "columns": 5, "ext": "mhtml", "format": "sb1 - 160x90 (storyboard)", "format_id": "sb1", "format_note": "storyboard", "fps": 0.10024529844644317, "fragments": [{"duration": 249.38825448613377, "url": "https://i.ytimg.com/sb/00xeNL3vdQo/storyboard3_L2/M0.jpg?sqp=-oaymwENSDfyq4qpAwVwAcABBqLzl_8DBgi7ydSvBg==&sigh=rs$AOn4CLCs5JXqFszxpTya656B5XrTgfnqjQ"}, {"duration": 249.38825448613377, "url": "https://i.ytimg.com/sb/00xeNL3vdQo/storyboard3_L2/M1.jpg?sqp=-oaymwENSDfyq4qpAwVwAcABBqLzl_8DBgi7ydSvBg==&sigh=rs$AOn4CLCs5JXqFszxpTya656B5XrTgfnqjQ"}, {"duration": 249.38825448613377, "url": "https://i.ytimg.com/sb/00xeNL3vdQo/storyboard3_L2/M2.jpg?sqp=-oaymwENSDfyq4qpAwVwAcABBqLzl_8DBgi7ydSvBg==&sigh=rs$AOn4CLCs5JXqFszxpTya656B5XrTgfnqjQ"}, {"duration": 249.38825448613377, "url": "https://i.ytimg.com/sb/00xeNL3vdQo/storyboard3_L2/M3.jpg?sqp=-oaymwENSDfyq4qpAwVwAcABBqLzl_8DBgi7ydSvBg==&sigh=rs$AOn4CLCs5JXqFszxpTya656B5XrTgfnqjQ"}, {"duration": 249.38825448613377, "url": "https://i.ytimg.com/sb/00xeNL3vdQo/storyboard3_L2/M4.jpg?sqp=-oaymwENSDfyq4qpAwVwAcABBqLzl_8DBgi7ydSvBg==&sigh=rs$AOn4CLCs5JXqFszxpTya656B5XrTgfnqjQ"}, {"duration": 249.38825448613377, "url": "https://i.ytimg.com/sb/00xeNL3vdQo/storyboard3_L2/M5.jpg?sqp=-oaymwENSDfyq4qpAwVwAcABBqLzl_8DBgi7ydSvBg==&sigh=rs$AOn4CLCs5JXqFszxpTya656B5XrTgfnqjQ"}, {"duration": 249.38825448613377, "url": "https://i.ytimg.com/sb/00xeNL3vdQo/storyboard3_L2/M6.jpg?sqp=-oaymwENSDfyq4qpAwVwAcABBqLzl_8DBgi7ydSvBg==&sigh=rs$AOn4CLCs5JXqFszxpTya656B5XrTgfnqjQ"}, {"duration": 249.38825448613377, "url": "https://i.ytimg.com/sb/00xeNL3vdQo/storyboard3_L2/M7.jpg?sqp=-oaymwENSDfyq4qpAwVwAcABBqLzl_8DBgi7ydSvBg==&sigh=rs$AOn4CLCs5JXqFszxpTya656B5XrTgfnqjQ"}, {"duration": 249.38825448613377, "url": "https://i.ytimg.com/sb/00xeNL3vdQo/storyboard3_L2/M8.jpg?sqp=-oaymwENSDfyq4qpAwVwAcABBqLzl_8DBgi7ydSvBg==&sigh=rs$AOn4CLCs5JXqFszxpTya656B5XrTgfnqjQ"}, {"duration": 249.38825448613377, "url": "https://i.ytimg.com/sb/00xeNL3vdQo/storyboard3_L2/M9.jpg?sqp=-oaymwENSDfyq4qpAwVwAcABBqLzl_8DBgi7ydSvBg==&sigh=rs$AOn4CLCs5JXqFszxpTya656B5XrTgfnqjQ"}, {"duration": 249.38825448613377, "url": "https://i.ytimg.com/sb/00xeNL3vdQo/storyboard3_L2/M10.jpg?sqp=-oaymwENSDfyq4qpAwVwAcABBqLzl_8DBgi7ydSvBg==&sigh=rs$AOn4CLCs5JXqFszxpTya656B5XrTgfnqjQ"}, {"duration": 249.38825448613377, "url": "https://i.ytimg.com/sb/00xeNL3vdQo/storyboard3_L2/M11.jpg?sqp=-oaymwENSDfyq4qpAwVwAcABBqLzl_8DBgi7ydSvBg==&sigh=rs$AOn4CLCs5JXqFszxpTya656B5XrTgfnqjQ"}, {"duration": 249.38825448613377, "url": "https://i.ytimg.com/sb/00xeNL3vdQo/storyboard3_L2/M12.jpg?sqp=-oaymwENSDfyq4qpAwVwAcABBqLzl_8DBgi7ydSvBg==&sigh=rs$AOn4CLCs5JXqFszxpTya656B5XrTgfnqjQ"}, {"duration": 249.38825448613377, "url": "https://i.ytimg.com/sb/00xeNL3vdQo/storyboard3_L2/M13.jpg?sqp=-oaymwENSDfyq4qpAwVwAcABBqLzl_8DBgi7ydSvBg==&sigh=rs$AOn4CLCs5JXqFszxpTya656B5XrTgfnqjQ"}, {"duration": 249.38825448613377, "url": "https://i.ytimg.com/sb/00xeNL3vdQo/storyboard3_L2/M14.jpg?sqp=-oaymwENSDfyq4qpAwVwAcABBqLzl_8DBgi7ydSvBg==&sigh=rs$AOn4CLCs5JXqFszxpTya656B5XrTgfnqjQ"}, {"duration": 249.38825448613377, "url": "https://i.ytimg.com/sb/00xeNL3vdQo/storyboard3_L2/M15.jpg?sqp=-oaymwENSDfyq4qpAwVwAcABBqLzl_8DBgi7ydSvBg==&sigh=rs$AOn4CLCs5JXqFszxpTya656B5XrTgfnqjQ"}, {"duration": 249.38825448613377, "url": "https://i.ytimg.com/sb/00xeNL3vdQo/storyboard3_L2/M16.jpg?sqp=-oaymwENSDfyq4qpAwVwAcABBqLzl_8DBgi7ydSvBg==&sigh=rs$AOn4CLCs5JXqFszxpTya656B5XrTgfnqjQ"}, {"duration": 249.38825448613377, "url": "https://i.ytimg.com/sb/00xeNL3vdQo/storyboard3_L2/M17.jpg?sqp=-oaymwENSDfyq4qpAwVwAcABBqLzl_8DBgi7ydSvBg==&sigh=rs$AOn4CLCs5JXqFszxpTya656B5XrTgfnqjQ"}, {"duration": 249.38825448613377, "url": "https://i.ytimg.com/sb/00xeNL3vdQo/storyboard3_L2/M18.jpg?sqp=-oaymwENSDfyq4qpAwVwAcABBqLzl_8DBgi7ydSvBg==&sigh=rs$AOn4CLCs5JXqFszxpTya656B5XrTgfnqjQ"}, {"duration": 249.38825448613377, "url": "https://i.ytimg.com/sb/00xeNL3vdQo/storyboard3_L2/M19.jpg?sqp=-oaymwENSDfyq4qpAwVwAcABBqLzl_8DBgi7ydSvBg==&sigh=rs$AOn4CLCs5JXqFszxpTya656B5XrTgfnqjQ"}, {"duration": 249.38825448613377, "url": "https://i.ytimg.com/sb/00xeNL3vdQo/storyboard3_L2/M20.jpg?sqp=-oaymwENSDfyq4qpAwVwAcABBqLzl_8DBgi7ydSvBg==&sigh=rs$AOn4CLCs5JXqFszxpTya656B5XrTgfnqjQ"}, {"duration": 249.38825448613377, "url": "https://i.ytimg.com/sb/00xeNL3vdQo/storyboard3_L2/M21.jpg?sqp=-oaymwENSDfyq4qpAwVwAcABBqLzl_8DBgi7ydSvBg==&sigh=rs$AOn4CLCs5JXqFszxpTya656B5XrTgfnqjQ"}, {"duration": 249.38825448613377, "url": "https://i.ytimg.com/sb/00xeNL3vdQo/storyboard3_L2/M22.jpg?sqp=-oaymwENSDfyq4qpAwVwAcABBqLzl_8DBgi7ydSvBg==&sigh=rs$AOn4CLCs5JXqFszxpTya656B5XrTgfnqjQ"}, {"duration": 249.38825448613377, "url": "https://i.ytimg.com/sb/00xeNL3vdQo/storyboard3_L2/M23.jpg?sqp=-oaymwENSDfyq4qpAwVwAcABBqLzl_8DBgi7ydSvBg==&sigh=rs$AOn4CLCs5JXqFszxpTya656B5XrTgfnqjQ"}, {"duration": 129.68189233278918, "url": "https://i.ytimg.com/sb/00xeNL3vdQo/storyboard3_L2/M24.jpg?sqp=-oaymwENSDfyq4qpAwVwAcABBqLzl_8DBgi7ydSvBg==&sigh=rs$AOn4CLCs5JXqFszxpTya656B5XrTgfnqjQ"}], "height": 90, "http_headers": {"Accept": "text/html,application/xhtml+xml,application/xml;q=0.9,*/*;q=0.8", "Accept-Language": "en-us,en;q=0.5", "Sec-Fetch-Mode": "navigate", "User-Agent": "Mozilla/5.0 (Windows NT 10.0; Win64; x64) AppleWebKit/537.36 (KHTML, like Gecko) Chrome/92.0.4515.159 Safari/537.36"}, "protocol": "mhtml", "resolution": "160x90", "rows": 5, "url": "https://i.ytimg.com/sb/00xeNL3vdQo/storyboard3_L2/M$M.jpg?sqp=-oaymwENSDfyq4qpAwVwAcABBqLzl_8DBgi7ydSvBg==&sigh=rs$AOn4CLCs5JXqFszxpTya656B5XrTgfnqjQ", "vbr": 0, "vcodec": "none", "video_ext": "none", "width": 160}, {"abr": 0, "acodec": "none", "aspect_ratio": 1.78, "audio_ext": "none", "columns": 3, "ext": "mhtml", "format": "sb0 - 320x180 (storyboard)", "format_id": "sb0", "format_note": "storyboard", "fps": 0.10024529844644317, "fragments": [{"duration": 89.77977161500816, "url": "https://i.ytimg.com/sb/00xeNL3vdQo/storyboard3_L3/M0.jpg?sqp=-oaymwENSDfyq4qpAwVwAcABBqLzl_8DBgi7ydSvBg==&sigh=rs$AOn4CLAjSPevZHh6G45AVVs0TWev30vpAg"}, {"duration": 89.77977161500816, "url": "https://i.ytimg.com/sb/00xeNL3vdQo/storyboard3_L3/M1.jpg?sqp=-oaymwENSDfyq4qpAwVwAcABBqLzl_8DBgi7ydSvBg==&sigh=rs$AOn4CLAjSPevZHh6G45AVVs0TWev30vpAg"}, {"duration": 89.77977161500816, "url": "https://i.ytimg.com/sb/00xeNL3vdQo/storyboard3_L3/M2.jpg?sqp=-oaymwENSDfyq4qpAwVwAcABBqLzl_8DBgi7ydSvBg==&sigh=rs$AOn4CLAjSPevZHh6G45AVVs0TWev30vpAg"}, {"duration": 89.77977161500816, "url": "https://i.ytimg.com/sb/00xeNL3vdQo/storyboard3_L3/M3.jpg?sqp=-oaymwENSDfyq4qpAwVwAcABBqLzl_8DBgi7ydSvBg==&sigh=rs$AOn4CLAjSPevZHh6G45AVVs0TWev30vpAg"}, {"duration": 89.77977161500816, "url": "https://i.ytimg.com/sb/00xeNL3vdQo/storyboard3_L3/M4.jpg?sqp=-oaymwENSDfyq4qpAwVwAcABBqLzl_8DBgi7ydSvBg==&sigh=rs$AOn4CLAjSPevZHh6G45AVVs0TWev30vpAg"}, {"duration": 89.77977161500816, "url": "https://i.ytimg.com/sb/00xeNL3vdQo/storyboard3_L3/M5.jpg?sqp=-oaymwENSDfyq4qpAwVwAcABBqLzl_8DBgi7ydSvBg==&sigh=rs$AOn4CLAjSPevZHh6G45AVVs0TWev30vpAg"}, {"duration": 89.77977161500816, "url": "https://i.ytimg.com/sb/00xeNL3vdQo/storyboard3_L3/M6.jpg?sqp=-oaymwENSDfyq4qpAwVwAcABBqLzl_8DBgi7ydSvBg==&sigh=rs$AOn4CLAjSPevZHh6G45AVVs0TWev30vpAg"}, {"duration": 89.77977161500816, "url": "https://i.ytimg.com/sb/00xeNL3vdQo/storyboard3_L3/M7.jpg?sqp=-oaymwENSDfyq4qpAwVwAcABBqLzl_8DBgi7ydSvBg==&sigh=rs$AOn4CLAjSPevZHh6G45AVVs0TWev30vpAg"}, {"duration": 89.77977161500816, "url": "https://i.ytimg.com/sb/00xeNL3vdQo/storyboard3_L3/M8.jpg?sqp=-oaymwENSDfyq4qpAwVwAcABBqLzl_8DBgi7ydSvBg==&sigh=rs$AOn4CLAjSPevZHh6G45AVVs0TWev30vpAg"}, {"duration": 89.77977161500816, "url": "https://i.ytimg.com/sb/00xeNL3vdQo/storyboard3_L3/M9.jpg?sqp=-oaymwENSDfyq4qpAwVwAcABBqLzl_8DBgi7ydSvBg==&sigh=rs$AOn4CLAjSPevZHh6G45AVVs0TWev30vpAg"}, {"duration": 89.77977161500816, "url": "https://i.ytimg.com/sb/00xeNL3vdQo/storyboard3_L3/M10.jpg?sqp=-oaymwENSDfyq4qpAwVwAcABBqLzl_8DBgi7ydSvBg==&sigh=rs$AOn4CLAjSPevZHh6G45AVVs0TWev30vpAg"}, {"duration": 89.77977161500816, "url": "https://i.ytimg.com/sb/00xeNL3vdQo/storyboard3_L3/M11.jpg?sqp=-oaymwENSDfyq4qpAwVwAcABBqLzl_8DBgi7ydSvBg==&sigh=rs$AOn4CLAjSPevZHh6G45AVVs0TWev30vpAg"}, {"duration": 89.77977161500816, "url": "https://i.ytimg.com/sb/00xeNL3vdQo/storyboard3_L3/M12.jpg?sqp=-oaymwENSDfyq4qpAwVwAcABBqLzl_8DBgi7ydSvBg==&sigh=rs$AOn4CLAjSPevZHh6G45AVVs0TWev30vpAg"}, {"duration": 89.77977161500816, "url": "https://i.ytimg.com/sb/00xeNL3vdQo/storyboard3_L3/M13.jpg?sqp=-oaymwENSDfyq4qpAwVwAcABBqLzl_8DBgi7ydSvBg==&sigh=rs$AOn4CLAjSPevZHh6G45AVVs0TWev30vpAg"}, {"duration": 89.77977161500816, "url": "https://i.ytimg.com/sb/00xeNL3vdQo/storyboard3_L3/M14.jpg?sqp=-oaymwENSDfyq4qpAwVwAcABBqLzl_8DBgi7ydSvBg==&sigh=rs$AOn4CLAjSPevZHh6G45AVVs0TWev30vpAg"}, {"duration": 89.77977161500816, "url": "https://i.ytimg.com/sb/00xeNL3vdQo/storyboard3_L3/M15.jpg?sqp=-oaymwENSDfyq4qpAwVwAcABBqLzl_8DBgi7ydSvBg==&sigh=rs$AOn4CLAjSPevZHh6G45AVVs0TWev30vpAg"}, {"duration": 89.77977161500816, "url": "https://i.ytimg.com/sb/00xeNL3vdQo/storyboard3_L3/M16.jpg?sqp=-oaymwENSDfyq4qpAwVwAcABBqLzl_8DBgi7ydSvBg==&sigh=rs$AOn4CLAjSPevZHh6G45AVVs0TWev30vpAg"}, {"duration": 89.77977161500816, "url": "https://i.ytimg.com/sb/00xeNL3vdQo/storyboard3_L3/M17.jpg?sqp=-oaymwENSDfyq4qpAwVwAcABBqLzl_8DBgi7ydSvBg==&sigh=rs$AOn4CLAjSPevZHh6G45AVVs0TWev30vpAg"}, {"duration": 89.77977161500816, "url": "https://i.ytimg.com/sb/00xeNL3vdQo/storyboard3_L3/M18.jpg?sqp=-oaymwENSDfyq4qpAwVwAcABBqLzl_8DBgi7ydSvBg==&sigh=rs$AOn4CLAjSPevZHh6G45AVVs0TWev30vpAg"}, {"duration": 89.77977161500816, "url": "https://i.ytimg.com/sb/00xeNL3vdQo/storyboard3_L3/M19.jpg?sqp=-oaymwENSDfyq4qpAwVwAcABBqLzl_8DBgi7ydSvBg==&sigh=rs$AOn4CLAjSPevZHh6G45AVVs0TWev30vpAg"}, {"duration": 89.77977161500816, "url": "https://i.ytimg.com/sb/00xeNL3vdQo/storyboard3_L3/M20.jpg?sqp=-oaymwENSDfyq4qpAwVwAcABBqLzl_8DBgi7ydSvBg==&sigh=rs$AOn4CLAjSPevZHh6G45AVVs0TWev30vpAg"}, {"duration": 89.77977161500816, "url": "https://i.ytimg.com/sb/00xeNL3vdQo/storyboard3_L3/M21.jpg?sqp=-oaymwENSDfyq4qpAwVwAcABBqLzl_8DBgi7ydSvBg==&sigh=rs$AOn4CLAjSPevZHh6G45AVVs0TWev30vpAg"}, {"duration": 89.77977161500816, "url": "https://i.ytimg.com/sb/00xeNL3vdQo/storyboard3_L3/M22.jpg?sqp=-oaymwENSDfyq4qpAwVwAcABBqLzl_8DBgi7ydSvBg==&sigh=rs$AOn4CLAjSPevZHh6G45AVVs0TWev30vpAg"}, {"duration": 89.77977161500816, "url": "https://i.ytimg.com/sb/00xeNL3vdQo/storyboard3_L3/M23.jpg?sqp=-oaymwENSDfyq4qpAwVwAcABBqLzl_8DBgi7ydSvBg==&sigh=rs$AOn4CLAjSPevZHh6G45AVVs0TWev30vpAg"}, {"duration": 89.77977161500816, "url": "https://i.ytimg.com/sb/00xeNL3vdQo/storyboard3_L3/M24.jpg?sqp=-oaymwENSDfyq4qpAwVwAcABBqLzl_8DBgi7ydSvBg==&sigh=rs$AOn4CLAjSPevZHh6G45AVVs0TWev30vpAg"}, {"duration": 89.77977161500816, "url": "https://i.ytimg.com/sb/00xeNL3vdQo/storyboard3_L3/M25.jpg?sqp=-oaymwENSDfyq4qpAwVwAcABBqLzl_8DBgi7ydSvBg==&sigh=rs$AOn4CLAjSPevZHh6G45AVVs0TWev30vpAg"}, {"duration": 89.77977161500816, "url": "https://i.ytimg.com/sb/00xeNL3vdQo/storyboard3_L3/M26.jpg?sqp=-oaymwENSDfyq4qpAwVwAcABBqLzl_8DBgi7ydSvBg==&sigh=rs$AOn4CLAjSPevZHh6G45AVVs0TWev30vpAg"}, {"duration": 89.77977161500816, "url": "https://i.ytimg.com/sb/00xeNL3vdQo/storyboard3_L3/M27.jpg?sqp=-oaymwENSDfyq4qpAwVwAcABBqLzl_8DBgi7ydSvBg==&sigh=rs$AOn4CLAjSPevZHh6G45AVVs0TWev30vpAg"}, {"duration": 89.77977161500816, "url": "https://i.ytimg.com/sb/00xeNL3vdQo/storyboard3_L3/M28.jpg?sqp=-oaymwENSDfyq4qpAwVwAcABBqLzl_8DBgi7ydSvBg==&sigh=rs$AOn4CLAjSPevZHh6G45AVVs0TWev30vpAg"}, {"duration": 89.77977161500816, "url": "https://i.ytimg.com/sb/00xeNL3vdQo/storyboard3_L3/M29.jpg?sqp=-oaymwENSDfyq4qpAwVwAcABBqLzl_8DBgi7ydSvBg==&sigh=rs$AOn4CLAjSPevZHh6G45AVVs0TWev30vpAg"}, {"duration": 89.77977161500816, "url": "https://i.ytimg.com/sb/00xeNL3vdQo/storyboard3_L3/M30.jpg?sqp=-oaymwENSDfyq4qpAwVwAcABBqLzl_8DBgi7ydSvBg==&sigh=rs$AOn4CLAjSPevZHh6G45AVVs0TWev30vpAg"}, {"duration": 89.77977161500816, "url": "https://i.ytimg.com/sb/00xeNL3vdQo/storyboard3_L3/M31.jpg?sqp=-oaymwENSDfyq4qpAwVwAcABBqLzl_8DBgi7ydSvBg==&sigh=rs$AOn4CLAjSPevZHh6G45AVVs0TWev30vpAg"}, {"duration": 89.77977161500816, "url": "https://i.ytimg.com/sb/00xeNL3vdQo/storyboard3_L3/M32.jpg?sqp=-oaymwENSDfyq4qpAwVwAcABBqLzl_8DBgi7ydSvBg==&sigh=rs$AOn4CLAjSPevZHh6G45AVVs0TWev30vpAg"}, {"duration": 89.77977161500816, "url": "https://i.ytimg.com/sb/00xeNL3vdQo/storyboard3_L3/M33.jpg?sqp=-oaymwENSDfyq4qpAwVwAcABBqLzl_8DBgi7ydSvBg==&sigh=rs$AOn4CLAjSPevZHh6G45AVVs0TWev30vpAg"}, {"duration": 89.77977161500816, "url": "https://i.ytimg.com/sb/00xeNL3vdQo/storyboard3_L3/M34.jpg?sqp=-oaymwENSDfyq4qpAwVwAcABBqLzl_8DBgi7ydSvBg==&sigh=rs$AOn4CLAjSPevZHh6G45AVVs0TWev30vpAg"}, {"duration": 89.77977161500816, "url": "https://i.ytimg.com/sb/00xeNL3vdQo/storyboard3_L3/M35.jpg?sqp=-oaymwENSDfyq4qpAwVwAcABBqLzl_8DBgi7ydSvBg==&sigh=rs$AOn4CLAjSPevZHh6G45AVVs0TWev30vpAg"}, {"duration": 89.77977161500816, "url": "https://i.ytimg.com/sb/00xeNL3vdQo/storyboard3_L3/M36.jpg?sqp=-oaymwENSDfyq4qpAwVwAcABBqLzl_8DBgi7ydSvBg==&sigh=rs$AOn4CLAjSPevZHh6G45AVVs0TWev30vpAg"}, {"duration": 89.77977161500816, "url": "https://i.ytimg.com/sb/00xeNL3vdQo/storyboard3_L3/M37.jpg?sqp=-oaymwENSDfyq4qpAwVwAcABBqLzl_8DBgi7ydSvBg==&sigh=rs$AOn4CLAjSPevZHh6G45AVVs0TWev30vpAg"}, {"duration": 89.77977161500816, "url": "https://i.ytimg.com/sb/00xeNL3vdQo/storyboard3_L3/M38.jpg?sqp=-oaymwENSDfyq4qpAwVwAcABBqLzl_8DBgi7ydSvBg==&sigh=rs$AOn4CLAjSPevZHh6G45AVVs0TWev30vpAg"}, {"duration": 89.77977161500816, "url": "https://i.ytimg.com/sb/00xeNL3vdQo/storyboard3_L3/M39.jpg?sqp=-oaymwENSDfyq4qpAwVwAcABBqLzl_8DBgi7ydSvBg==&sigh=rs$AOn4CLAjSPevZHh6G45AVVs0TWev30vpAg"}, {"duration": 89.77977161500816, "url": "https://i.ytimg.com/sb/00xeNL3vdQo/storyboard3_L3/M40.jpg?sqp=-oaymwENSDfyq4qpAwVwAcABBqLzl_8DBgi7ydSvBg==&sigh=rs$AOn4CLAjSPevZHh6G45AVVs0TWev30vpAg"}, {"duration": 89.77977161500816, "url": "https://i.ytimg.com/sb/00xeNL3vdQo/storyboard3_L3/M41.jpg?sqp=-oaymwENSDfyq4qpAwVwAcABBqLzl_8DBgi7ydSvBg==&sigh=rs$AOn4CLAjSPevZHh6G45AVVs0TWev30vpAg"}, {"duration": 89.77977161500816, "url": "https://i.ytimg.com/sb/00xeNL3vdQo/storyboard3_L3/M42.jpg?sqp=-oaymwENSDfyq4qpAwVwAcABBqLzl_8DBgi7ydSvBg==&sigh=rs$AOn4CLAjSPevZHh6G45AVVs0TWev30vpAg"}, {"duration": 89.77977161500816, "url": "https://i.ytimg.com/sb/00xeNL3vdQo/storyboard3_L3/M43.jpg?sqp=-oaymwENSDfyq4qpAwVwAcABBqLzl_8DBgi7ydSvBg==&sigh=rs$AOn4CLAjSPevZHh6G45AVVs0TWev30vpAg"}, {"duration": 89.77977161500816, "url": "https://i.ytimg.com/sb/00xeNL3vdQo/storyboard3_L3/M44.jpg?sqp=-oaymwENSDfyq4qpAwVwAcABBqLzl_8DBgi7ydSvBg==&sigh=rs$AOn4CLAjSPevZHh6G45AVVs0TWev30vpAg"}, {"duration": 89.77977161500816, "url": "https://i.ytimg.com/sb/00xeNL3vdQo/storyboard3_L3/M45.jpg?sqp=-oaymwENSDfyq4qpAwVwAcABBqLzl_8DBgi7ydSvBg==&sigh=rs$AOn4CLAjSPevZHh6G45AVVs0TWev30vpAg"}, {"duration": 89.77977161500816, "url": "https://i.ytimg.com/sb/00xeNL3vdQo/storyboard3_L3/M46.jpg?sqp=-oaymwENSDfyq4qpAwVwAcABBqLzl_8DBgi7ydSvBg==&sigh=rs$AOn4CLAjSPevZHh6G45AVVs0TWev30vpAg"}, {"duration": 89.77977161500816, "url": "https://i.ytimg.com/sb/00xeNL3vdQo/storyboard3_L3/M47.jpg?sqp=-oaymwENSDfyq4qpAwVwAcABBqLzl_8DBgi7ydSvBg==&sigh=rs$AOn4CLAjSPevZHh6G45AVVs0TWev30vpAg"}, {"duration": 89.77977161500816, "url": "https://i.ytimg.com/sb/00xeNL3vdQo/storyboard3_L3/M48.jpg?sqp=-oaymwENSDfyq4qpAwVwAcABBqLzl_8DBgi7ydSvBg==&sigh=rs$AOn4CLAjSPevZHh6G45AVVs0TWev30vpAg"}, {"duration": 89.77977161500816, "url": "https://i.ytimg.com/sb/00xeNL3vdQo/storyboard3_L3/M49.jpg?sqp=-oaymwENSDfyq4qpAwVwAcABBqLzl_8DBgi7ydSvBg==&sigh=rs$AOn4CLAjSPevZHh6G45AVVs0TWev30vpAg"}, {"duration": 89.77977161500816, "url": "https://i.ytimg.com/sb/00xeNL3vdQo/storyboard3_L3/M50.jpg?sqp=-oaymwENSDfyq4qpAwVwAcABBqLzl_8DBgi7ydSvBg==&sigh=rs$AOn4CLAjSPevZHh6G45AVVs0TWev30vpAg"}, {"duration": 89.77977161500816, "url": "https://i.ytimg.com/sb/00xeNL3vdQo/storyboard3_L3/M51.jpg?sqp=-oaymwENSDfyq4qpAwVwAcABBqLzl_8DBgi7ydSvBg==&sigh=rs$AOn4CLAjSPevZHh6G45AVVs0TWev30vpAg"}, {"duration": 89.77977161500816, "url": "https://i.ytimg.com/sb/00xeNL3vdQo/storyboard3_L3/M52.jpg?sqp=-oaymwENSDfyq4qpAwVwAcABBqLzl_8DBgi7ydSvBg==&sigh=rs$AOn4CLAjSPevZHh6G45AVVs0TWev30vpAg"}, {"duration": 89.77977161500816, "url": "https://i.ytimg.com/sb/00xeNL3vdQo/storyboard3_L3/M53.jpg?sqp=-oaymwENSDfyq4qpAwVwAcABBqLzl_8DBgi7ydSvBg==&sigh=rs$AOn4CLAjSPevZHh6G45AVVs0TWev30vpAg"}, {"duration": 89.77977161500816, "url": "https://i.ytimg.com/sb/00xeNL3vdQo/storyboard3_L3/M54.jpg?sqp=-oaymwENSDfyq4qpAwVwAcABBqLzl_8DBgi7ydSvBg==&sigh=rs$AOn4CLAjSPevZHh6G45AVVs0TWev30vpAg"}, {"duration": 89.77977161500816, "url": "https://i.ytimg.com/sb/00xeNL3vdQo/storyboard3_L3/M55.jpg?sqp=-oaymwENSDfyq4qpAwVwAcABBqLzl_8DBgi7ydSvBg==&sigh=rs$AOn4CLAjSPevZHh6G45AVVs0TWev30vpAg"}, {"duration": 89.77977161500816, "url": "https://i.ytimg.com/sb/00xeNL3vdQo/storyboard3_L3/M56.jpg?sqp=-oaymwENSDfyq4qpAwVwAcABBqLzl_8DBgi7ydSvBg==&sigh=rs$AOn4CLAjSPevZHh6G45AVVs0TWev30vpAg"}, {"duration": 89.77977161500816, "url": "https://i.ytimg.com/sb/00xeNL3vdQo/storyboard3_L3/M57.jpg?sqp=-oaymwENSDfyq4qpAwVwAcABBqLzl_8DBgi7ydSvBg==&sigh=rs$AOn4CLAjSPevZHh6G45AVVs0TWev30vpAg"}, {"duration": 89.77977161500816, "url": "https://i.ytimg.com/sb/00xeNL3vdQo/storyboard3_L3/M58.jpg?sqp=-oaymwENSDfyq4qpAwVwAcABBqLzl_8DBgi7ydSvBg==&sigh=rs$AOn4CLAjSPevZHh6G45AVVs0TWev30vpAg"}, {"duration": 89.77977161500816, "url": "https://i.ytimg.com/sb/00xeNL3vdQo/storyboard3_L3/M59.jpg?sqp=-oaymwENSDfyq4qpAwVwAcABBqLzl_8DBgi7ydSvBg==&sigh=rs$AOn4CLAjSPevZHh6G45AVVs0TWev30vpAg"}, {"duration": 89.77977161500816, "url": "https://i.ytimg.com/sb/00xeNL3vdQo/storyboard3_L3/M60.jpg?sqp=-oaymwENSDfyq4qpAwVwAcABBqLzl_8DBgi7ydSvBg==&sigh=rs$AOn4CLAjSPevZHh6G45AVVs0TWev30vpAg"}, {"duration": 89.77977161500816, "url": "https://i.ytimg.com/sb/00xeNL3vdQo/storyboard3_L3/M61.jpg?sqp=-oaymwENSDfyq4qpAwVwAcABBqLzl_8DBgi7ydSvBg==&sigh=rs$AOn4CLAjSPevZHh6G45AVVs0TWev30vpAg"}, {"duration": 89.77977161500816, "url": "https://i.ytimg.com/sb/00xeNL3vdQo/storyboard3_L3/M62.jpg?sqp=-oaymwENSDfyq4qpAwVwAcABBqLzl_8DBgi7ydSvBg==&sigh=rs$AOn4CLAjSPevZHh6G45AVVs0TWev30vpAg"}, {"duration": 89.77977161500816, "url": "https://i.ytimg.com/sb/00xeNL3vdQo/storyboard3_L3/M63.jpg?sqp=-oaymwENSDfyq4qpAwVwAcABBqLzl_8DBgi7ydSvBg==&sigh=rs$AOn4CLAjSPevZHh6G45AVVs0TWev30vpAg"}, {"duration": 89.77977161500816, "url": "https://i.ytimg.com/sb/00xeNL3vdQo/storyboard3_L3/M64.jpg?sqp=-oaymwENSDfyq4qpAwVwAcABBqLzl_8DBgi7ydSvBg==&sigh=rs$AOn4CLAjSPevZHh6G45AVVs0TWev30vpAg"}, {"duration": 89.77977161500816, "url": "https://i.ytimg.com/sb/00xeNL3vdQo/storyboard3_L3/M65.jpg?sqp=-oaymwENSDfyq4qpAwVwAcABBqLzl_8DBgi7ydSvBg==&sigh=rs$AOn4CLAjSPevZHh6G45AVVs0TWev30vpAg"}, {"duration": 89.77977161500816, "url": "https://i.ytimg.com/sb/00xeNL3vdQo/storyboard3_L3/M66.jpg?sqp=-oaymwENSDfyq4qpAwVwAcABBqLzl_8DBgi7ydSvBg==&sigh=rs$AOn4CLAjSPevZHh6G45AVVs0TWev30vpAg"}, {"duration": 89.77977161500816, "url": "https://i.ytimg.com/sb/00xeNL3vdQo/storyboard3_L3/M67.jpg?sqp=-oaymwENSDfyq4qpAwVwAcABBqLzl_8DBgi7ydSvBg==&sigh=rs$AOn4CLAjSPevZHh6G45AVVs0TWev30vpAg"}, {"duration": 9.975530179444831, "url": "https://i.ytimg.com/sb/00xeNL3vdQo/storyboard3_L3/M68.jpg?sqp=-oaymwENSDfyq4qpAwVwAcABBqLzl_8DBgi7ydSvBg==&sigh=rs$AOn4CLAjSPevZHh6G45AVVs0TWev30vpAg"}], "height": 180, "http_headers": {"Accept": "text/html,application/xhtml+xml,application/xml;q=0.9,*/*;q=0.8", "Accept-Language": "en-us,en;q=0.5", "Sec-Fetch-Mode": "navigate", "User-Agent": "Mozilla/5.0 (Windows NT 10.0; Win64; x64) AppleWebKit/537.36 (KHTML, like Gecko) Chrome/92.0.4515.159 Safari/537.36"}, "protocol": "mhtml", "resolution": "320x180", "rows": 3, "url": "https://i.ytimg.com/sb/00xeNL3vdQo/storyboard3_L3/M$M.jpg?sqp=-oaymwENSDfyq4qpAwVwAcABBqLzl_8DBgi7ydSvBg==&sigh=rs$AOn4CLAjSPevZHh6G45AVVs0TWev30vpAg", "vbr": 0, "vcodec": "none", "video_ext": "none", "width": 320}, {"abr": 129.472, "acodec": "mp4a.40.2", "asr": 44100, "audio_channels": 2, "audio_ext": "m4a", "container": "m4a_dash", "downloader_options": {"http_chunk_size": 10485760}, "ext": "m4a", "filesize": 98966382, "filesize_approx": 98966244, "format": "140 - audio only (medium)", "format_id": "140", "format_note": "medium", "has_drm": false, "http_headers": {"Accept": "text/html,application/xhtml+xml,application/xml;q=0.9,*/*;q=0.8", "Accept-Language": "en-us,en;q=0.5", "Sec-Fetch-Mode": "navigate", "User-Agent": "Mozilla/5.0 (Windows NT 10.0; Win64; x64) AppleWebKit/537.36 (KHTML, like Gecko) Chrome/92.0.4515.159 Safari/537.36"}, "language_preference": -1, "protocol": "https", "quality": 3.0, "resolution": "audio only", "source_preference": -1, "tbr": 129.472, "url": "https://rr2---sn-2gb7sn7y.googlevideo.com/videoplayback?expire=1735084295&ei=p_RqZ9D6CK7r6dsP4NDiUA&ip=78.80.167.40&id=o-AEZA9Rj-xdw0fNy3KwCQ_Rf8DsjbZe6x1dK42PAqwbFR&itag=140&source=youtube&requiressl=yes&xpc=EgVo2aDSNQ%3D%3D&met=1735062695%2C&mh=fL&mm=31%2C29&mn=sn-2gb7sn7y%2Csn-2gb7snez&ms=au%2Crdu&mv=m&mvi=2&pl=21&rms=au%2Cau&initcwndbps=2428750&siu=1&bui=AfMhrI8UUtfJFmlWA0P1NeAleRhYXtuSzltbcsSfL5zzFfhSrIIeB-HSk9S2WDsX36ct0863Fg&spc=x-caUPJUU24pl0MZR7CTDF7b4tCF-XKGiYd2whAttb0W6S_axAmkWjWbJ-P6Rm6ffg&vprv=1&svpuc=1&mime=audio%2Fmp4&ns=nScaY93FuzSjzcW-gG5nYqIQ&rqh=1&gir=yes&clen=98966382&dur=6115.067&lmt=1710564600260058&mt=1735062329&fvip=1&keepalive=yes&fexp=51326932%2C51335594&c=WEB_CREATOR&sefc=1&txp=7308224&n=h4qEtGkeb2GfrQ&sparams=expire%2Cei%2Cip%2Cid%2Citag%2Csource%2Crequiressl%2Cxpc%2Csiu%2Cbui%2Cspc%2Cvprv%2Csvpuc%2Cmime%2Cns%2Crqh%2Cgir%2Cclen%2Cdur%2Clmt&lsparams=met%2Cmh%2Cmm%2Cmn%2Cms%2Cmv%2Cmvi%2Cpl%2Crms%2Cinitcwndbps&lsig=AGluJ3MwRQIgcKFmRA9PckzcKOKwkhfqjAA76g3SxGGB44ThN7t-VRwCIQCDP7ZVJmBAVdsWitPfyMoUzwubCXIdBKwiKuuWN0D_QQ%3D%3D&sig=AJfQdSswRAIgC5w1Gzu7VN5wGLibV8Quq15H3pgYg325xD9FzUr42DUCIAReAwqNJVlNF2FowUJFC7HV8ijmUxl40b1bwiRndm6Z", "vbr": 0, "vcodec": "none", "video_ext": "none"}, {"abr": 127.552, "acodec": "opus", "asr": 48000, "audio_channels": 2, "audio_ext": "webm", "container": "webm_dash", "downloader_options": {"http_chunk_size": 10485760}, "ext": "webm", "filesize": 97498420, "filesize_approx": 97498213, "format": "251 - audio only (medium)", "format_id": "251", "format_note": "medium", "has_drm": false, "http_headers": {"Accept": "text/html,application/xhtml+xml,application/xml;q=0.9,*/*;q=0.8", "Accept-Language": "en-us,en;q=0.5", "Sec-Fetch-Mode": "navigate", "User-Agent": "Mozilla/5.0 (Windows NT 10.0; Win64; x64) AppleWebKit/537.36 (KHTML, like Gecko) Chrome/92.0.4515.159 Safari/537.36"}, "language_preference": -1, "protocol": "https", "quality": 3.0, "resolution": "audio only", "source_preference": -1, "tbr": 127.552, "url": "https://rr2---sn-2gb7sn7y.googlevideo.com/videoplayback?expire=1735084295&ei=p_RqZ9D6CK7r6dsP4NDiUA&ip=78.80.167.40&id=o-AEZA9Rj-xdw0fNy3KwCQ_Rf8DsjbZe6x1dK42PAqwbFR&itag=251&source=youtube&requiressl=yes&xpc=EgVo2aDSNQ%3D%3D&met=1735062695%2C&mh=fL&mm=31%2C29&mn=sn-2gb7sn7y%2Csn-2gb7snez&ms=au%2Crdu&mv=m&mvi=2&pl=21&rms=au%2Cau&initcwndbps=2428750&siu=1&bui=AfMhrI8UUtfJFmlWA0P1NeAleRhYXtuSzltbcsSfL5zzFfhSrIIeB-HSk9S2WDsX36ct0863Fg&spc=x-caUPJUU24pl0MZR7CTDF7b4tCF-XKGiYd2whAttb0W6S_axAmkWjWbJ-P6Rm6ffg&vprv=1&svpuc=1&mime=audio%2Fwebm&ns=nScaY93FuzSjzcW-gG5nYqIQ&rqh=1&gir=yes&clen=97498420&dur=6115.041&lmt=1710564619991519&mt=1735062329&fvip=1&keepalive=yes&fexp=51326932%2C51335594&c=WEB_CREATOR&sefc=1&txp=7308224&n=h4qEtGkeb2GfrQ&sparams=expire%2Cei%2Cip%2Cid%2Citag%2Csource%2Crequiressl%2Cxpc%2Csiu%2Cbui%2Cspc%2Cvprv%2Csvpuc%2Cmime%2Cns%2Crqh%2Cgir%2Cclen%2Cdur%2Clmt&lsparams=met%2Cmh%2Cmm%2Cmn%2Cms%2Cmv%2Cmvi%2Cpl%2Crms%2Cinitcwndbps&lsig=AGluJ3MwRQIgcKFmRA9PckzcKOKwkhfqjAA76g3SxGGB44ThN7t-VRwCIQCDP7ZVJmBAVdsWitPfyMoUzwubCXIdBKwiKuuWN0D_QQ%3D%3D&sig=AJfQdSswRQIhAN4ehmXqB7H1aYwkiSYwcqu8wkO_ir8E-HifKa5xB_YkAiBM7puL6AzKSLRPZJg1iXpbxBeqhFhzUSpFsxLS1oN47g%3D%3D", "vbr": 0, "vcodec": "none", "video_ext": "none"}, {"abr": 65.063, "acodec": "opus", "asr": 48000, "audio_channels": 2, "audio_ext": "webm", "container": "webm_dash", "downloader_options": {"http_chunk_size": 10485760}, "ext": "webm", "filesize": 49733019, "filesize_approx": 49732864, "format": "250 - audio only (low)", "format_id": "250", "format_note": "low", "has_drm": false, "http_headers": {"Accept": "text/html,application/xhtml+xml,application/xml;q=0.9,*/*;q=0.8", "Accept-Language": "en-us,en;q=0.5", "Sec-Fetch-Mode": "navigate", "User-Agent": "Mozilla/5.0 (Windows NT 10.0; Win64; x64) AppleWebKit/537.36 (KHTML, like Gecko) Chrome/92.0.4515.159 Safari/537.36"}, "language_preference": -1, "protocol": "https", "quality": 2.0, "resolution": "audio only", "source_preference": -1, "tbr": 65.063, "url": "https://rr2---sn-2gb7sn7y.googlevideo.com/videoplayback?expire=1735084295&ei=p_RqZ9D6CK7r6dsP4NDiUA&ip=78.80.167.40&id=o-AEZA9Rj-xdw0fNy3KwCQ_Rf8DsjbZe6x1dK42PAqwbFR&itag=250&source=youtube&requiressl=yes&xpc=EgVo2aDSNQ%3D%3D&met=1735062695%2C&mh=fL&mm=31%2C29&mn=sn-2gb7sn7y%2Csn-2gb7snez&ms=au%2Crdu&mv=m&mvi=2&pl=21&rms=au%2Cau&initcwndbps=2428750&siu=1&bui=AfMhrI8UUtfJFmlWA0P1NeAleRhYXtuSzltbcsSfL5zzFfhSrIIeB-HSk9S2WDsX36ct0863Fg&spc=x-caUPJUU24pl0MZR7CTDF7b4tCF-XKGiYd2whAttb0W6S_axAmkWjWbJ-P6Rm6ffg&vprv=1&svpuc=1&mime=audio%2Fwebm&ns=nScaY93FuzSjzcW-gG5nYqIQ&rqh=1&gir=yes&clen=49733019&dur=6115.041&lmt=1710564619991619&mt=1735062329&fvip=1&keepalive=yes&fexp=51326932%2C51335594&c=WEB_CREATOR&sefc=1&txp=7308224&n=h4qEtGkeb2GfrQ&sparams=expire%2Cei%2Cip%2Cid%2Citag%2Csource%2Crequiressl%2Cxpc%2Csiu%2Cbui%2Cspc%2Cvprv%2Csvpuc%2Cmime%2Cns%2Crqh%2Cgir%2Cclen%2Cdur%2Clmt&lsparams=met%2Cmh%2Cmm%2Cmn%2Cms%2Cmv%2Cmvi%2Cpl%2Crms%2Cinitcwndbps&lsig=AGluJ3MwRQIgcKFmRA9PckzcKOKwkhfqjAA76g3SxGGB44ThN7t-VRwCIQCDP7ZVJmBAVdsWitPfyMoUzwubCXIdBKwiKuuWN0D_QQ%3D%3D&sig=AJfQdSswRQIhAOwRyCE8915rl3BDOqlaYXf49kz9NEhGkVFSMAXGdYbtAiB3sR1DXvfUQdG-gVlK3w_RggVN6cAHOUwkK9BezZvG6w%3D%3D", "vbr": 0, "vcodec": "none", "video_ext": "none"}, {"abr": 49.397, "acodec": "opus", "asr": 48000, "audio_channels": 2, "audio_ext": "webm", "container": "webm_dash", "downloader_options": {"http_chunk_size": 10485760}, "ext": "webm", "filesize": 37758511, "filesize_approx": 37758085, "format": "249 - audio only (low)", "format_id": "249", "format_note": "low", "has_drm": false, "http_headers": {"Accept": "text/html,application/xhtml+xml,application/xml;q=0.9,*/*;q=0.8", "Accept-Language": "en-us,en;q=0.5", "Sec-Fetch-Mode": "navigate", "User-Agent": "Mozilla/5.0 (Windows NT 10.0; Win64; x64) AppleWebKit/537.36 (KHTML, like Gecko) Chrome/92.0.4515.159 Safari/537.36"}, "language_preference": -1, "protocol": "https", "quality": 2.0, "resolution": "audio only", "source_preference": -1, "tbr": 49.397, "url": "https://rr2---sn-2gb7sn7y.googlevideo.com/videoplayback?expire=1735084295&ei=p_RqZ9D6CK7r6dsP4NDiUA&ip=78.80.167.40&id=o-AEZA9Rj-xdw0fNy3KwCQ_Rf8DsjbZe6x1dK42PAqwbFR&itag=249&source=youtube&requiressl=yes&xpc=EgVo2aDSNQ%3D%3D&met=1735062695%2C&mh=fL&mm=31%2C29&mn=sn-2gb7sn7y%2Csn-2gb7snez&ms=au%2Crdu&mv=m&mvi=2&pl=21&rms=au%2Cau&initcwndbps=2428750&siu=1&bui=AfMhrI8UUtfJFmlWA0P1NeAleRhYXtuSzltbcsSfL5zzFfhSrIIeB-HSk9S2WDsX36ct0863Fg&spc=x-caUPJUU24pl0MZR7CTDF7b4tCF-XKGiYd2whAttb0W6S_axAmkWjWbJ-P6Rm6ffg&vprv=1&svpuc=1&mime=audio%2Fwebm&ns=nScaY93FuzSjzcW-gG5nYqIQ&rqh=1&gir=yes&clen=37758511&dur=6115.041&lmt=1710564619991655&mt=1735062329&fvip=1&keepalive=yes&fexp=51326932%2C51335594&c=WEB_CREATOR&sefc=1&txp=7308224&n=h4qEtGkeb2GfrQ&sparams=expire%2Cei%2Cip%2Cid%2Citag%2Csource%2Crequiressl%2Cxpc%2Csiu%2Cbui%2Cspc%2Cvprv%2Csvpuc%2Cmime%2Cns%2Crqh%2Cgir%2Cclen%2Cdur%2Clmt&lsparams=met%2Cmh%2Cmm%2Cmn%2Cms%2Cmv%2Cmvi%2Cpl%2Crms%2Cinitcwndbps&lsig=AGluJ3MwRQIgcKFmRA9PckzcKOKwkhfqjAA76g3SxGGB44ThN7t-VRwCIQCDP7ZVJmBAVdsWitPfyMoUzwubCXIdBKwiKuuWN0D_QQ%3D%3D&sig=AJfQdSswRgIhAIftAzW0qoTZuhSGuR0C6tSxtFpz21fN4riLUCz8KnPHAiEA8f5jsBIU02b47P40HLE53lbgpvv7SzkPTraWnk6YFuc%3D", "vbr": 0, "vcodec": "none", "video_ext": "none"}, {"abr": 33.887, "acodec": "opus", "asr": 48000, "audio_channels": 2, "audio_ext": "webm", "container": "webm_dash", "downloader_options": {"http_chunk_size": 10485760}, "ext": "webm", "filesize": 25902964, "filesize_approx": 25902549, "format": "600 - audio only (ultralow)", "format_id": "600", "format_note": "ultralow", "has_drm": false, "http_headers": {"Accept": "text/html,application/xhtml+xml,application/xml;q=0.9,*/*;q=0.8", "Accept-Language": "en-us,en;q=0.5", "Sec-Fetch-Mode": "navigate", "User-Agent": "Mozilla/5.0 (Windows NT 10.0; Win64; x64) AppleWebKit/537.36 (KHTML, like Gecko) Chrome/92.0.4515.159 Safari/537.36"}, "language_preference": -1, "protocol": "https", "quality": 1.0, "resolution": "audio only", "source_preference": -1, "tbr": 33.887, "url": "https://rr1---sn-2gb7snez.googlevideo.com/videoplayback?expire=1735084295&ei=p_RqZ6igEeTi6dsPi77KyQU&ip=78.80.167.40&id=o-AC0wiWbzedkChxzzacgW8yzNWR9XAImmR4Ttl_SH-ynR&itag=600&source=youtube&requiressl=yes&xpc=EgVo2aDSNQ%3D%3D&met=1735062695%2C&mh=fL&mm=31%2C26&mn=sn-2gb7snez%2Csn-c0q7lnz7&ms=au%2Conr&mv=m&mvi=1&pl=21&rms=au%2Cau&initcwndbps=2288750&siu=1&bui=AfMhrI9B8C1ad2TEjuVUQXvRcJuys5dij3TafRBWz6__IXVnVooMPRSXQK6K88JQyoodqwxzjw&vprv=1&svpuc=1&mime=audio%2Fwebm&ns=V37ev8fvNAZwHt8_Ko58tW4Q&rqh=1&gir=yes&clen=25902964&dur=6115.041&lmt=1710564620031767&mt=1735062329&fvip=2&keepalive=yes&fexp=51326932%2C51331020%2C51335594&c=MWEB&sefc=1&txp=7308224&n=l-9iOvVIChTUpQ&sparams=expire%2Cei%2Cip%2Cid%2Citag%2Csource%2Crequiressl%2Cxpc%2Csiu%2Cbui%2Cvprv%2Csvpuc%2Cmime%2Cns%2Crqh%2Cgir%2Cclen%2Cdur%2Clmt&lsparams=met%2Cmh%2Cmm%2Cmn%2Cms%2Cmv%2Cmvi%2Cpl%2Crms%2Cinitcwndbps&lsig=AGluJ3MwRQIhAN7qMZex9PfxvHburkPwnYwaKqOIfNgDcg9FzZ5Jm2siAiACAIqbMEJ5YX6D0euX5WpM2GKq3_X-wEk2UaExPZ7_YQ%3D%3D&sig=AJfQdSswRgIhALQE1LDrHVdU4aBZYRrtT0rnbuxfm4IQdovinZKQNq7VAiEAoMQX5Llc_7NQscQNtoDEUt7E0oiW7IDO5TvVMhJij_k%3D", "vbr": 0, "vcodec": "none", "video_ext": "none"}, {"abr": 30.783, "acodec": "mp4a.40.5", "asr": 22050, "audio_channels": 2, "audio_ext": "m4a", "container": "m4a_dash", "downloader_options": {"http_chunk_size": 10485760}, "ext": "m4a", "filesize": 23530782, "filesize_approx": 23530371, "format": "599 - audio only (ultralow)", "format_id": "599", "format_note": "ultralow", "has_drm": false, "http_headers": {"Accept": "text/html,application/xhtml+xml,application/xml;q=0.9,*/*;q=0.8", "Accept-Language": "en-us,en;q=0.5", "Sec-Fetch-Mode": "navigate", "User-Agent": "Mozilla/5.0 (Windows NT 10.0; Win64; x64) AppleWebKit/537.36 (KHTML, like Gecko) Chrome/92.0.4515.159 Safari/537.36"}, "language_preference": -1, "protocol": "https", "quality": 1.0, "resolution": "audio only", "source_preference": -1, "tbr": 30.783, "url": "https://rr1---sn-2gb7snez.googlevideo.com/videoplayback?expire=1735084295&ei=p_RqZ6igEeTi6dsPi77KyQU&ip=78.80.167.40&id=o-AC0wiWbzedkChxzzacgW8yzNWR9XAImmR4Ttl_SH-ynR&itag=599&source=youtube&requiressl=yes&xpc=EgVo2aDSNQ%3D%3D&met=1735062695%2C&mh=fL&mm=31%2C26&mn=sn-2gb7snez%2Csn-c0q7lnz7&ms=au%2Conr&mv=m&mvi=1&pl=21&rms=au%2Cau&initcwndbps=2288750&siu=1&bui=AfMhrI9B8C1ad2TEjuVUQXvRcJuys5dij3TafRBWz6__IXVnVooMPRSXQK6K88JQyoodqwxzjw&vprv=1&svpuc=1&mime=audio%2Fmp4&ns=V37ev8fvNAZwHt8_Ko58tW4Q&rqh=1&gir=yes&clen=23530782&dur=6115.160&lmt=1710564444576966&mt=1735062329&fvip=2&keepalive=yes&fexp=51326932%2C51331020%2C51335594&c=MWEB&sefc=1&txp=7308224&n=l-9iOvVIChTUpQ&sparams=expire%2Cei%2Cip%2Cid%2Citag%2Csource%2Crequiressl%2Cxpc%2Csiu%2Cbui%2Cvprv%2Csvpuc%2Cmime%2Cns%2Crqh%2Cgir%2Cclen%2Cdur%2Clmt&lsparams=met%2Cmh%2Cmm%2Cmn%2Cms%2Cmv%2Cmvi%2Cpl%2Crms%2Cinitcwndbps&lsig=AGluJ3MwRQIhAN7qMZex9PfxvHburkPwnYwaKqOIfNgDcg9FzZ5Jm2siAiACAIqbMEJ5YX6D0euX5WpM2GKq3_X-wEk2UaExPZ7_YQ%3D%3D&sig=AJfQdSswRQIgK2h0G3NuoDGqenkVWbBI6Jt4vm6ObOdUAxgFLAWSxPECIQCoAw3wWt8a7SwzW2fZ9oZOhy_xxkmrkqjHaWr-3MJWyg%3D%3D", "vbr": 0, "vcodec": "none", "video_ext": "none"}, {"abr": 0, "acodec": "none", "aspect_ratio": 1.78, "audio_ext": "none", "container": "mp4_dash", "downloader_options": {"http_chunk_size": 10485760}, "dynamic_range": "SDR", "ext": "mp4", "filesize": 1642416708, "filesize_approx": 1642416384, "format": "137 - 1920x1080 (1080p)", "format_id": "137", "format_note": "1080p", "fps": 30, "has_drm": false, "height": 1080, "http_headers": {"Accept": "text/html,application/xhtml+xml,application/xml;q=0.9,*/*;q=0.8", "Accept-Language": "en-us,en;q=0.5", "Sec-Fetch-Mode": "navigate", "User-Agent": "Mozilla/5.0 (Windows NT 10.0; Win64; x64) AppleWebKit/537.36 (KHTML, like Gecko) Chrome/92.0.4515.159 Safari/537.36"}, "language_preference": -1, "protocol": "https", "quality": 9.0, "resolution": "1920x1080", "source_preference": -1, "tbr": 2148.705, "url": "https://rr2---sn-2gb7sn7y.googlevideo.com/videoplayback?expire=1735084295&ei=p_RqZ9D6CK7r6dsP4NDiUA&ip=78.80.167.40&id=o-AEZA9Rj-xdw0fNy3KwCQ_Rf8DsjbZe6x1dK42PAqwbFR&itag=137&aitags=133%2C134%2C135%2C136%2C137%2C160%2C242%2C243%2C244%2C247%2C248%2C278&source=youtube&requiressl=yes&xpc=EgVo2aDSNQ%3D%3D&met=1735062695%2C&mh=fL&mm=31%2C29&mn=sn-2gb7sn7y%2Csn-2gb7snez&ms=au%2Crdu&mv=m&mvi=2&pl=21&rms=au%2Cau&initcwndbps=2428750&siu=1&bui=AfMhrI8UUtfJFmlWA0P1NeAleRhYXtuSzltbcsSfL5zzFfhSrIIeB-HSk9S2WDsX36ct0863Fg&spc=x-caUPJUU24pl0MZR7CTDF7b4tCF-XKGiYd2whAttb0W6S_axAmkWjWbJ-P6Rm6ffg&vprv=1&svpuc=1&mime=video%2Fmp4&ns=nScaY93FuzSjzcW-gG5nYqIQ&rqh=1&gir=yes&clen=1642416708&dur=6115.000&lmt=1710564467342657&mt=1735062329&fvip=1&keepalive=yes&fexp=51326932%2C51335594&c=WEB_CREATOR&sefc=1&txp=7309224&n=h4qEtGkeb2GfrQ&sparams=expire%2Cei%2Cip%2Cid%2Caitags%2Csource%2Crequiressl%2Cxpc%2Csiu%2Cbui%2Cspc%2Cvprv%2Csvpuc%2Cmime%2Cns%2Crqh%2Cgir%2Cclen%2Cdur%2Clmt&lsparams=met%2Cmh%2Cmm%2Cmn%2Cms%2Cmv%2Cmvi%2Cpl%2Crms%2Cinitcwndbps&lsig=AGluJ3MwRQIgcKFmRA9PckzcKOKwkhfqjAA76g3SxGGB44ThN7t-VRwCIQCDP7ZVJmBAVdsWitPfyMoUzwubCXIdBKwiKuuWN0D_QQ%3D%3D&sig=AJfQdSswRgIhAMTNz4KC1k1z2m21U1AqgxblmSuylXKFKOQVDHVX7ZUSAiEA9vE8DyGC-jZiXqEJims8-EBMnGjw_kPABwq-I3fju9k%3D", "vbr": 2148.705, "vcodec": "avc1.640028", "video_ext": "mp4", "width": 1920}, {"abr": 0, "acodec": "none", "aspect_ratio": 1.78, "audio_ext": "none", "container": "webm_dash", "downloader_options": {"http_chunk_size": 10485760}, "dynamic_range": "SDR", "ext": "webm", "filesize": 872914505, "filesize_approx": 872913956, "format": "248 - 1920x1080 (1080p)", "format_id": "248", "format_note": "1080p", "fps": 30, "has_drm": false, "height": 1080, "http_headers": {"Accept": "text/html,application/xhtml+xml,application/xml;q=0.9,*/*;q=0.8", "Accept-Language": "en-us,en;q=0.5", "Sec-Fetch-Mode": "navigate", "User-Agent": "Mozilla/5.0 (Windows NT 10.0; Win64; x64) AppleWebKit/537.36 (KHTML, like Gecko) Chrome/92.0.4515.159 Safari/537.36"}, "language_preference": -1, "protocol": "https", "quality": 9.0, "resolution": "1920x1080", "source_preference": -1, "tbr": 1141.997, "url": "https://rr2---sn-2gb7sn7y.googlevideo.com/videoplayback?expire=1735084295&ei=p_RqZ9D6CK7r6dsP4NDiUA&ip=78.80.167.40&id=o-AEZA9Rj-xdw0fNy3KwCQ_Rf8DsjbZe6x1dK42PAqwbFR&itag=248&aitags=133%2C134%2C135%2C136%2C137%2C160%2C242%2C243%2C244%2C247%2C248%2C278&source=youtube&requiressl=yes&xpc=EgVo2aDSNQ%3D%3D&met=1735062695%2C&mh=fL&mm=31%2C29&mn=sn-2gb7sn7y%2Csn-2gb7snez&ms=au%2Crdu&mv=m&mvi=2&pl=21&rms=au%2Cau&initcwndbps=2428750&siu=1&bui=AfMhrI8UUtfJFmlWA0P1NeAleRhYXtuSzltbcsSfL5zzFfhSrIIeB-HSk9S2WDsX36ct0863Fg&spc=x-caUPJUU24pl0MZR7CTDF7b4tCF-XKGiYd2whAttb0W6S_axAmkWjWbJ-P6Rm6ffg&vprv=1&svpuc=1&mime=video%2Fwebm&ns=nScaY93FuzSjzcW-gG5nYqIQ&rqh=1&gir=yes&clen=872914505&dur=6115.000&lmt=1710564465383720&mt=1735062329&fvip=1&keepalive=yes&fexp=51326932%2C51335594&c=WEB_CREATOR&sefc=1&txp=730F224&n=h4qEtGkeb2GfrQ&sparams=expire%2Cei%2Cip%2Cid%2Caitags%2Csource%2Crequiressl%2Cxpc%2Csiu%2Cbui%2Cspc%2Cvprv%2Csvpuc%2Cmime%2Cns%2Crqh%2Cgir%2Cclen%2Cdur%2Clmt&lsparams=met%2Cmh%2Cmm%2Cmn%2Cms%2Cmv%2Cmvi%2Cpl%2Crms%2Cinitcwndbps&lsig=AGluJ3MwRQIgcKFmRA9PckzcKOKwkhfqjAA76g3SxGGB44ThN7t-VRwCIQCDP7ZVJmBAVdsWitPfyMoUzwubCXIdBKwiKuuWN0D_QQ%3D%3D&sig=AJfQdSswRQIhANxlnaw9IQMxN0JsDVS6LkjGqDdty9cAFuOCUqL_ZAh1AiBZ5cSB69yBoqkaaGeQ2_77glUbcn-BP0KXvql0WFBONQ%3D%3D", "vbr": 1141.997, "vcodec": "vp9", "video_ext": "webm", "width": 1920}, {"abr": 0, "acodec": "none", "aspect_ratio": 1.78, "audio_ext": "none", "container": "mp4_dash", "downloader_options": {"http_chunk_size": 10485760}, "dynamic_range": "SDR", "ext": "mp4", "filesize": 846873767, "filesize_approx": 846873229, "format": "136 - 1280x720 (720p)", "format_id": "136", "format_note": "720p", "fps": 30, "has_drm": false, "height": 720, "http_headers": {"Accept": "text/html,application/xhtml+xml,application/xml;q=0.9,*/*;q=0.8", "Accept-Language": "en-us,en;q=0.5", "Sec-Fetch-Mode": "navigate", "User-Agent": "Mozilla/5.0 (Windows NT 10.0; Win64; x64) AppleWebKit/537.36 (KHTML, like Gecko) Chrome/92.0.4515.159 Safari/537.36"}, "language_preference": -1, "protocol": "https", "quality": 8.0, "resolution": "1280x720", "source_preference": -1, "tbr": 1107.929, "url": "https://rr2---sn-2gb7sn7y.googlevideo.com/videoplayback?expire=1735084295&ei=p_RqZ9D6CK7r6dsP4NDiUA&ip=78.80.167.40&id=o-AEZA9Rj-xdw0fNy3KwCQ_Rf8DsjbZe6x1dK42PAqwbFR&itag=136&aitags=133%2C134%2C135%2C136%2C137%2C160%2C242%2C243%2C244%2C247%2C248%2C278&source=youtube&requiressl=yes&xpc=EgVo2aDSNQ%3D%3D&met=1735062695%2C&mh=fL&mm=31%2C29&mn=sn-2gb7sn7y%2Csn-2gb7snez&ms=au%2Crdu&mv=m&mvi=2&pl=21&rms=au%2Cau&initcwndbps=2428750&siu=1&bui=AfMhrI8UUtfJFmlWA0P1NeAleRhYXtuSzltbcsSfL5zzFfhSrIIeB-HSk9S2WDsX36ct0863Fg&spc=x-caUPJUU24pl0MZR7CTDF7b4tCF-XKGiYd2whAttb0W6S_axAmkWjWbJ-P6Rm6ffg&vprv=1&svpuc=1&mime=video%2Fmp4&ns=nScaY93FuzSjzcW-gG5nYqIQ&rqh=1&gir=yes&clen=846873767&dur=6115.000&lmt=1710564445821861&mt=1735062329&fvip=1&keepalive=yes&fexp=51326932%2C51335594&c=WEB_CREATOR&sefc=1&txp=7309224&n=h4qEtGkeb2GfrQ&sparams=expire%2Cei%2Cip%2Cid%2Caitags%2Csource%2Crequiressl%2Cxpc%2Csiu%2Cbui%2Cspc%2Cvprv%2Csvpuc%2Cmime%2Cns%2Crqh%2Cgir%2Cclen%2Cdur%2Clmt&lsparams=met%2Cmh%2Cmm%2Cmn%2Cms%2Cmv%2Cmvi%2Cpl%2Crms%2Cinitcwndbps&lsig=AGluJ3MwRQIgcKFmRA9PckzcKOKwkhfqjAA76g3SxGGB44ThN7t-VRwCIQCDP7ZVJmBAVdsWitPfyMoUzwubCXIdBKwiKuuWN0D_QQ%3D%3D&sig=AJfQdSswRQIhAKsaQYm8qDjKwXO3wdon2bfBW2nqMhk4HU7mBU0qxNngAiBQplimZYpwbfheeveRwkCqpCfsHnnKuc49Jz5RM2Ak9A%3D%3D", "vbr": 1107.929, "vcodec": "avc1.64001f", "video_ext": "mp4", "width": 1280}, {"abr": 0, "acodec": "none", "aspect_ratio": 1.78, "audio_ext": "none", "container": "webm_dash", "downloader_options": {"http_chunk_size": 10485760}, "dynamic_range": "SDR", "ext": "webm", "filesize": 596528345, "filesize_approx": 596528186, "format": "247 - 1280x720 (720p)", "format_id": "247", "format_note": "720p", "fps": 30, "has_drm": false, "height": 720, "http_headers": {"Accept": "text/html,application/xhtml+xml,application/xml;q=0.9,*/*;q=0.8", "Accept-Language": "en-us,en;q=0.5", "Sec-Fetch-Mode": "navigate", "User-Agent": "Mozilla/5.0 (Windows NT 10.0; Win64; x64) AppleWebKit/537.36 (KHTML, like Gecko) Chrome/92.0.4515.159 Safari/537.36"}, "language_preference": -1, "protocol": "https", "quality": 8.0, "resolution": "1280x720", "source_preference": -1, "tbr": 780.413, "url": "https://rr2---sn-2gb7sn7y.googlevideo.com/videoplayback?expire=1735084295&ei=p_RqZ9D6CK7r6dsP4NDiUA&ip=78.80.167.40&id=o-AEZA9Rj-xdw0fNy3KwCQ_Rf8DsjbZe6x1dK42PAqwbFR&itag=247&aitags=133%2C134%2C135%2C136%2C137%2C160%2C242%2C243%2C244%2C247%2C248%2C278&source=youtube&requiressl=yes&xpc=EgVo2aDSNQ%3D%3D&met=1735062695%2C&mh=fL&mm=31%2C29&mn=sn-2gb7sn7y%2Csn-2gb7snez&ms=au%2Crdu&mv=m&mvi=2&pl=21&rms=au%2Cau&initcwndbps=2428750&siu=1&bui=AfMhrI8UUtfJFmlWA0P1NeAleRhYXtuSzltbcsSfL5zzFfhSrIIeB-HSk9S2WDsX36ct0863Fg&spc=x-caUPJUU24pl0MZR7CTDF7b4tCF-XKGiYd2whAttb0W6S_axAmkWjWbJ-P6Rm6ffg&vprv=1&svpuc=1&mime=video%2Fwebm&ns=nScaY93FuzSjzcW-gG5nYqIQ&rqh=1&gir=yes&clen=596528345&dur=6115.000&lmt=1710564460260427&mt=1735062329&fvip=1&keepalive=yes&fexp=51326932%2C51335594&c=WEB_CREATOR&sefc=1&txp=730F224&n=h4qEtGkeb2GfrQ&sparams=expire%2Cei%2Cip%2Cid%2Caitags%2Csource%2Crequiressl%2Cxpc%2Csiu%2Cbui%2Cspc%2Cvprv%2Csvpuc%2Cmime%2Cns%2Crqh%2Cgir%2Cclen%2Cdur%2Clmt&lsparams=met%2Cmh%2Cmm%2Cmn%2Cms%2Cmv%2Cmvi%2Cpl%2Crms%2Cinitcwndbps&lsig=AGluJ3MwRQIgcKFmRA9PckzcKOKwkhfqjAA76g3SxGGB44ThN7t-VRwCIQCDP7ZVJmBAVdsWitPfyMoUzwubCXIdBKwiKuuWN0D_QQ%3D%3D&sig=AJfQdSswRgIhAM9oVarlJvh5QQRjSCOR_IvoldBoOR8ikaCE_spf0rNSAiEAoHsQF_q9yfd1Uo3sOQFzK7FPGFrp2_untfjXmRq0wYY%3D", "vbr": 780.413, "vcodec": "vp9", "video_ext": "webm", "width": 1280}, {"abr": 0, "acodec": "none", "aspect_ratio": 1.78, "audio_ext": "none", "container": "mp4_dash", "downloader_options": {"http_chunk_size": 10485760}, "dynamic_range": "SDR", "ext": "mp4", "filesize": 436848597, "filesize_approx": 436847956, "format": "135 - 854x480 (480p)", "format_id": "135", "format_note": "480p", "fps": 30, "has_drm": false, "height": 480, "http_headers": {"Accept": "text/html,application/xhtml+xml,application/xml;q=0.9,*/*;q=0.8", "Accept-Language": "en-us,en;q=0.5", "Sec-Fetch-Mode": "navigate", "User-Agent": "Mozilla/5.0 (Windows NT 10.0; Win64; x64) AppleWebKit/537.36 (KHTML, like Gecko) Chrome/92.0.4515.159 Safari/537.36"}, "language_preference": -1, "protocol": "https", "quality": 7.0, "resolution": "854x480", "source_preference": -1, "tbr": 571.51, "url": "https://rr2---sn-2gb7sn7y.googlevideo.com/videoplayback?expire=1735084295&ei=p_RqZ9D6CK7r6dsP4NDiUA&ip=78.80.167.40&id=o-AEZA9Rj-xdw0fNy3KwCQ_Rf8DsjbZe6x1dK42PAqwbFR&itag=135&aitags=133%2C134%2C135%2C136%2C137%2C160%2C242%2C243%2C244%2C247%2C248%2C278&source=youtube&requiressl=yes&xpc=EgVo2aDSNQ%3D%3D&met=1735062695%2C&mh=fL&mm=31%2C29&mn=sn-2gb7sn7y%2Csn-2gb7snez&ms=au%2Crdu&mv=m&mvi=2&pl=21&rms=au%2Cau&initcwndbps=2428750&siu=1&bui=AfMhrI8UUtfJFmlWA0P1NeAleRhYXtuSzltbcsSfL5zzFfhSrIIeB-HSk9S2WDsX36ct0863Fg&spc=x-caUPJUU24pl0MZR7CTDF7b4tCF-XKGiYd2whAttb0W6S_axAmkWjWbJ-P6Rm6ffg&vprv=1&svpuc=1&mime=video%2Fmp4&ns=nScaY93FuzSjzcW-gG5nYqIQ&rqh=1&gir=yes&clen=436848597&dur=6115.000&lmt=1710564443203516&mt=1735062329&fvip=1&keepalive=yes&fexp=51326932%2C51335594&c=WEB_CREATOR&sefc=1&txp=7309224&n=h4qEtGkeb2GfrQ&sparams=expire%2Cei%2Cip%2Cid%2Caitags%2Csource%2Crequiressl%2Cxpc%2Csiu%2Cbui%2Cspc%2Cvprv%2Csvpuc%2Cmime%2Cns%2Crqh%2Cgir%2Cclen%2Cdur%2Clmt&lsparams=met%2Cmh%2Cmm%2Cmn%2Cms%2Cmv%2Cmvi%2Cpl%2Crms%2Cinitcwndbps&lsig=AGluJ3MwRQIgcKFmRA9PckzcKOKwkhfqjAA76g3SxGGB44ThN7t-VRwCIQCDP7ZVJmBAVdsWitPfyMoUzwubCXIdBKwiKuuWN0D_QQ%3D%3D&sig=AJfQdSswRgIhAMFu39nuYDH6KkiSTIO5eyUcUXB2h3BBUuHN3VKLykGJAiEAhYO7jhzPq-Gi4y-KDNGJIFYystIlD3AR1OrOyzKbVzs%3D", "vbr": 571.51, "vcodec": "avc1.4d401f", "video_ext": "mp4", "width": 854}, {"acodec": "mp4a.40.2", "aspect_ratio": 1.78, "asr": 44100, "audio_channels": 2, "audio_ext": "none", "downloader_options": {"http_chunk_size": 10485760}, "dynamic_range": "SDR", "ext": "mp4", "filesize": 315969664, "filesize_approx": 315969333, "format": "18 - 640x360 (360p)", "format_id": "18", "format_note": "360p", "fps": 30, "has_drm": false, "height": 360, "http_headers": {"Accept": "text/html,application/xhtml+xml,application/xml;q=0.9,*/*;q=0.8", "Accept-Language": "en-us,en;q=0.5", "Sec-Fetch-Mode": "navigate", "User-Agent": "Mozilla/5.0 (Windows NT 10.0; Win64; x64) AppleWebKit/537.36 (KHTML, like Gecko) Chrome/92.0.4515.159 Safari/537.36"}, "language_preference": -1, "protocol": "https", "quality": 6.0, "resolution": "640x360", "source_preference": -1, "tbr": 413.365, "url": "https://rr2---sn-2gb7sn7y.googlevideo.com/videoplayback?expire=1735084295&ei=p_RqZ9D6CK7r6dsP4NDiUA&ip=78.80.167.40&id=o-AEZA9Rj-xdw0fNy3KwCQ_Rf8DsjbZe6x1dK42PAqwbFR&itag=18&source=youtube&requiressl=yes&xpc=EgVo2aDSNQ%3D%3D&met=1735062695%2C&mh=fL&mm=31%2C29&mn=sn-2gb7sn7y%2Csn-2gb7snez&ms=au%2Crdu&mv=m&mvi=2&pl=21&rms=au%2Cau&initcwndbps=2428750&siu=1&bui=AfMhrI98cKi0PcPSs8paOM_kwggxDQlV_Zv8KKqrYt5k6MQiRJm4XH1CRmUEYgYqi87mE9aBOw&spc=x-caUPJXU24pl0MZR7CTDF7b4tCF-XKGiYd2whAttb0W6S_axAmkWjWbJ-P6Rm6ve3Bx&vprv=1&svpuc=1&mime=video%2Fmp4&ns=xLZmydDIc5KMEB05YR4Q-1kQ&rqh=1&gir=yes&clen=315969664&ratebypass=yes&dur=6115.067&lmt=1710564410713901&mt=1735062329&fvip=1&fexp=51326932%2C51335594&c=WEB_CREATOR&sefc=1&txp=7309224&n=QFRb2Z_7-w0ejw&sparams=expire%2Cei%2Cip%2Cid%2Citag%2Csource%2Crequiressl%2Cxpc%2Csiu%2Cbui%2Cspc%2Cvprv%2Csvpuc%2Cmime%2Cns%2Crqh%2Cgir%2Cclen%2Cratebypass%2Cdur%2Clmt&lsparams=met%2Cmh%2Cmm%2Cmn%2Cms%2Cmv%2Cmvi%2Cpl%2Crms%2Cinitcwndbps&lsig=AGluJ3MwRQIgcKFmRA9PckzcKOKwkhfqjAA76g3SxGGB44ThN7t-VRwCIQCDP7ZVJmBAVdsWitPfyMoUzwubCXIdBKwiKuuWN0D_QQ%3D%3D&sig=AJfQdSswRgIhAKR62jfYQa1cwk3ExHSnNG9tdD-JB27OGPnqkZtZQRTVAiEA0VzVR_dm76CV0jyS2S8iLsxkjCdPOlJFWsI0yjELcZk%3D", "vcodec": "avc1.42001E", "video_ext": "mp4", "width": 640}, {"abr": 0, "acodec": "none", "aspect_ratio": 1.78, "audio_ext": "none", "container": "webm_dash", "downloader_options": {"http_chunk_size": 10485760}, "dynamic_range": "SDR", "ext": "webm", "filesize": 292473216, "filesize_approx": 292472806, "format": "244 - 854x480 (480p)", "format_id": "244", "format_note": "480p", "fps": 30, "has_drm": false, "height": 480, "http_headers": {"Accept": "text/html,application/xhtml+xml,application/xml;q=0.9,*/*;q=0.8", "Accept-Language": "en-us,en;q=0.5", "Sec-Fetch-Mode": "navigate", "User-Agent": "Mozilla/5.0 (Windows NT 10.0; Win64; x64) AppleWebKit/537.36 (KHTML, like Gecko) Chrome/92.0.4515.159 Safari/537.36"}, "language_preference": -1, "protocol": "https", "quality": 7.0, "resolution": "854x480", "source_preference": -1, "tbr": 382.63, "url": "https://rr2---sn-2gb7sn7y.googlevideo.com/videoplayback?expire=1735084295&ei=p_RqZ9D6CK7r6dsP4NDiUA&ip=78.80.167.40&id=o-AEZA9Rj-xdw0fNy3KwCQ_Rf8DsjbZe6x1dK42PAqwbFR&itag=244&aitags=133%2C134%2C135%2C136%2C137%2C160%2C242%2C243%2C244%2C247%2C248%2C278&source=youtube&requiressl=yes&xpc=EgVo2aDSNQ%3D%3D&met=1735062695%2C&mh=fL&mm=31%2C29&mn=sn-2gb7sn7y%2Csn-2gb7snez&ms=au%2Crdu&mv=m&mvi=2&pl=21&rms=au%2Cau&initcwndbps=2428750&siu=1&bui=AfMhrI8UUtfJFmlWA0P1NeAleRhYXtuSzltbcsSfL5zzFfhSrIIeB-HSk9S2WDsX36ct0863Fg&spc=x-caUPJUU24pl0MZR7CTDF7b4tCF-XKGiYd2whAttb0W6S_axAmkWjWbJ-P6Rm6ffg&vprv=1&svpuc=1&mime=video%2Fwebm&ns=nScaY93FuzSjzcW-gG5nYqIQ&rqh=1&gir=yes&clen=292473216&dur=6115.000&lmt=1710564450868929&mt=1735062329&fvip=1&keepalive=yes&fexp=51326932%2C51335594&c=WEB_CREATOR&sefc=1&txp=730F224&n=h4qEtGkeb2GfrQ&sparams=expire%2Cei%2Cip%2Cid%2Caitags%2Csource%2Crequiressl%2Cxpc%2Csiu%2Cbui%2Cspc%2Cvprv%2Csvpuc%2Cmime%2Cns%2Crqh%2Cgir%2Cclen%2Cdur%2Clmt&lsparams=met%2Cmh%2Cmm%2Cmn%2Cms%2Cmv%2Cmvi%2Cpl%2Crms%2Cinitcwndbps&lsig=AGluJ3MwRQIgcKFmRA9PckzcKOKwkhfqjAA76g3SxGGB44ThN7t-VRwCIQCDP7ZVJmBAVdsWitPfyMoUzwubCXIdBKwiKuuWN0D_QQ%3D%3D&sig=AJfQdSswRAIgAlYEg4ntOlaJNuGUGB6fMhZ2ZKWLmGAnbnTcTD7-JFACIBfz2I3xEVYm2IAWZZ5Z21WGHhRgAm6xiuy17X7mQqZe", "vbr": 382.63, "vcodec": "vp9", "video_ext": "webm", "width": 854}, {"abr": 0, "acodec": "none", "aspect_ratio": 1.78, "audio_ext": "none", "container": "mp4_dash", "downloader_options": {"http_chunk_size": 10485760}, "dynamic_range": "SDR", "ext": "mp4", "filesize": 241462092, "filesize_approx": 241461476, "format": "134 - 640x360 (360p)", "format_id": "134", "format_note": "360p", "fps": 30, "has_drm": false, "height": 360, "http_headers": {"Accept": "text/html,application/xhtml+xml,application/xml;q=0.9,*/*;q=0.8", "Accept-Language": "en-us,en;q=0.5", "Sec-Fetch-Mode": "navigate", "User-Agent": "Mozilla/5.0 (Windows NT 10.0; Win64; x64) AppleWebKit/537.36 (KHTML, like Gecko) Chrome/92.0.4515.159 Safari/537.36"}, "language_preference": -1, "protocol": "https", "quality": 6.0, "resolution": "640x360", "source_preference": -1, "tbr": 315.894, "url": "https://rr2---sn-2gb7sn7y.googlevideo.com/videoplayback?expire=1735084295&ei=p_RqZ9D6CK7r6dsP4NDiUA&ip=78.80.167.40&id=o-AEZA9Rj-xdw0fNy3KwCQ_Rf8DsjbZe6x1dK42PAqwbFR&itag=134&aitags=133%2C134%2C135%2C136%2C137%2C160%2C242%2C243%2C244%2C247%2C248%2C278&source=youtube&requiressl=yes&xpc=EgVo2aDSNQ%3D%3D&met=1735062695%2C&mh=fL&mm=31%2C29&mn=sn-2gb7sn7y%2Csn-2gb7snez&ms=au%2Crdu&mv=m&mvi=2&pl=21&rms=au%2Cau&initcwndbps=2428750&siu=1&bui=AfMhrI8UUtfJFmlWA0P1NeAleRhYXtuSzltbcsSfL5zzFfhSrIIeB-HSk9S2WDsX36ct0863Fg&spc=x-caUPJUU24pl0MZR7CTDF7b4tCF-XKGiYd2whAttb0W6S_axAmkWjWbJ-P6Rm6ffg&vprv=1&svpuc=1&mime=video%2Fmp4&ns=nScaY93FuzSjzcW-gG5nYqIQ&rqh=1&gir=yes&clen=241462092&dur=6115.000&lmt=1710564439996839&mt=1735062329&fvip=1&keepalive=yes&fexp=51326932%2C51335594&c=WEB_CREATOR&sefc=1&txp=7309224&n=h4qEtGkeb2GfrQ&sparams=expire%2Cei%2Cip%2Cid%2Caitags%2Csource%2Crequiressl%2Cxpc%2Csiu%2Cbui%2Cspc%2Cvprv%2Csvpuc%2Cmime%2Cns%2Crqh%2Cgir%2Cclen%2Cdur%2Clmt&lsparams=met%2Cmh%2Cmm%2Cmn%2Cms%2Cmv%2Cmvi%2Cpl%2Crms%2Cinitcwndbps&lsig=AGluJ3MwRQIgcKFmRA9PckzcKOKwkhfqjAA76g3SxGGB44ThN7t-VRwCIQCDP7ZVJmBAVdsWitPfyMoUzwubCXIdBKwiKuuWN0D_QQ%3D%3D&sig=AJfQdSswRgIhAIoOq9570vILxkXILsHtRYa0j5vpZAawj3oa3l1eyBXHAiEA-d7fUdLQjSWtNMMXWqkXj3z7IaHfj4A_NH39pMbIyhE%3D", "vbr": 315.894, "vcodec": "avc1.4d401e", "video_ext": "mp4", "width": 640}, {"abr": 0, "acodec": "none", "aspect_ratio": 1.78, "audio_ext": "none", "container": "webm_dash", "downloader_options": {"http_chunk_size": 10485760}, "dynamic_range": "SDR", "ext": "webm", "filesize": 171413635, "filesize_approx": 171413386, "format": "243 - 640x360 (360p)", "format_id": "243", "format_note": "360p", "fps": 30, "has_drm": false, "height": 360, "http_headers": {"Accept": "text/html,application/xhtml+xml,application/xml;q=0.9,*/*;q=0.8", "Accept-Language": "en-us,en;q=0.5", "Sec-Fetch-Mode": "navigate", "User-Agent": "Mozilla/5.0 (Windows NT 10.0; Win64; x64) AppleWebKit/537.36 (KHTML, like Gecko) Chrome/92.0.4515.159 Safari/537.36"}, "language_preference": -1, "protocol": "https", "quality": 6.0, "resolution": "640x360", "source_preference": -1, "tbr": 224.253, "url": "https://rr2---sn-2gb7sn7y.googlevideo.com/videoplayback?expire=1735084295&ei=p_RqZ9D6CK7r6dsP4NDiUA&ip=78.80.167.40&id=o-AEZA9Rj-xdw0fNy3KwCQ_Rf8DsjbZe6x1dK42PAqwbFR&itag=243&aitags=133%2C134%2C135%2C136%2C137%2C160%2C242%2C243%2C244%2C247%2C248%2C278&source=youtube&requiressl=yes&xpc=EgVo2aDSNQ%3D%3D&met=1735062695%2C&mh=fL&mm=31%2C29&mn=sn-2gb7sn7y%2Csn-2gb7snez&ms=au%2Crdu&mv=m&mvi=2&pl=21&rms=au%2Cau&initcwndbps=2428750&siu=1&bui=AfMhrI8UUtfJFmlWA0P1NeAleRhYXtuSzltbcsSfL5zzFfhSrIIeB-HSk9S2WDsX36ct0863Fg&spc=x-caUPJUU24pl0MZR7CTDF7b4tCF-XKGiYd2whAttb0W6S_axAmkWjWbJ-P6Rm6ffg&vprv=1&svpuc=1&mime=video%2Fwebm&ns=nScaY93FuzSjzcW-gG5nYqIQ&rqh=1&gir=yes&clen=171413635&dur=6115.000&lmt=1710564447337520&mt=1735062329&fvip=1&keepalive=yes&fexp=51326932%2C51335594&c=WEB_CREATOR&sefc=1&txp=730F224&n=h4qEtGkeb2GfrQ&sparams=expire%2Cei%2Cip%2Cid%2Caitags%2Csource%2Crequiressl%2Cxpc%2Csiu%2Cbui%2Cspc%2Cvprv%2Csvpuc%2Cmime%2Cns%2Crqh%2Cgir%2Cclen%2Cdur%2Clmt&lsparams=met%2Cmh%2Cmm%2Cmn%2Cms%2Cmv%2Cmvi%2Cpl%2Crms%2Cinitcwndbps&lsig=AGluJ3MwRQIgcKFmRA9PckzcKOKwkhfqjAA76g3SxGGB44ThN7t-VRwCIQCDP7ZVJmBAVdsWitPfyMoUzwubCXIdBKwiKuuWN0D_QQ%3D%3D&sig=AJfQdSswRAIgJCj_4RC3NGHiBiBSymlQl19PzsTTDkX6HmeCHv11iFkCIEcRfZ1fwzCozPjZQDGq06YzADT3rH6cG1LEA2lfNxxs", "vbr": 224.253, "vcodec": "vp9", "video_ext": "webm", "width": 640}, {"abr": 0, "acodec": "none", "aspect_ratio": 1.77, "audio_ext": "none", "container": "mp4_dash", "downloader_options": {"http_chunk_size": 10485760}, "dynamic_range": "SDR", "ext": "mp4", "filesize": 115834313, "filesize_approx": 115834151, "format": "133 - 426x240 (240p)", "format_id": "133", "format_note": "240p", "fps": 30, "has_drm": false, "height": 240, "http_headers": {"Accept": "text/html,application/xhtml+xml,application/xml;q=0.9,*/*;q=0.8", "Accept-Language": "en-us,en;q=0.5", "Sec-Fetch-Mode": "navigate", "User-Agent": "Mozilla/5.0 (Windows NT 10.0; Win64; x64) AppleWebKit/537.36 (KHTML, like Gecko) Chrome/92.0.4515.159 Safari/537.36"}, "language_preference": -1, "protocol": "https", "quality": 5.0, "resolution": "426x240", "source_preference": -1, "tbr": 151.541, "url": "https://rr2---sn-2gb7sn7y.googlevideo.com/videoplayback?expire=1735084295&ei=p_RqZ9D6CK7r6dsP4NDiUA&ip=78.80.167.40&id=o-AEZA9Rj-xdw0fNy3KwCQ_Rf8DsjbZe6x1dK42PAqwbFR&itag=133&aitags=133%2C134%2C135%2C136%2C137%2C160%2C242%2C243%2C244%2C247%2C248%2C278&source=youtube&requiressl=yes&xpc=EgVo2aDSNQ%3D%3D&met=1735062695%2C&mh=fL&mm=31%2C29&mn=sn-2gb7sn7y%2Csn-2gb7snez&ms=au%2Crdu&mv=m&mvi=2&pl=21&rms=au%2Cau&initcwndbps=2428750&siu=1&bui=AfMhrI8UUtfJFmlWA0P1NeAleRhYXtuSzltbcsSfL5zzFfhSrIIeB-HSk9S2WDsX36ct0863Fg&spc=x-caUPJUU24pl0MZR7CTDF7b4tCF-XKGiYd2whAttb0W6S_axAmkWjWbJ-P6Rm6ffg&vprv=1&svpuc=1&mime=video%2Fmp4&ns=nScaY93FuzSjzcW-gG5nYqIQ&rqh=1&gir=yes&clen=115834313&dur=6115.000&lmt=1710564440538658&mt=1735062329&fvip=1&keepalive=yes&fexp=51326932%2C51335594&c=WEB_CREATOR&sefc=1&txp=7309224&n=h4qEtGkeb2GfrQ&sparams=expire%2Cei%2Cip%2Cid%2Caitags%2Csource%2Crequiressl%2Cxpc%2Csiu%2Cbui%2Cspc%2Cvprv%2Csvpuc%2Cmime%2Cns%2Crqh%2Cgir%2Cclen%2Cdur%2Clmt&lsparams=met%2Cmh%2Cmm%2Cmn%2Cms%2Cmv%2Cmvi%2Cpl%2Crms%2Cinitcwndbps&lsig=AGluJ3MwRQIgcKFmRA9PckzcKOKwkhfqjAA76g3SxGGB44ThN7t-VRwCIQCDP7ZVJmBAVdsWitPfyMoUzwubCXIdBKwiKuuWN0D_QQ%3D%3D&sig=AJfQdSswRAIgOPCnJqboLQR4tTtv00GJ7OCfj9yx8rGGrM-zWjVBHgYCIGICgLssOUerXg6ejiw786IqUVFq7YtMF93yFixofLje", "vbr": 151.541, "vcodec": "avc1.4d4015", "video_ext": "mp4", "width": 426}, {"abr": 0, "acodec": "none", "aspect_ratio": 1.77, "audio_ext": "none", "container": "webm_dash", "downloader_options": {"http_chunk_size": 10485760}, "dynamic_range": "SDR", "ext": "webm", "filesize": 102713488, "filesize_approx": 102712890, "format": "242 - 426x240 (240p)", "format_id": "242", "format_note": "240p", "fps": 30, "has_drm": false, "height": 240, "http_headers": {"Accept": "text/html,application/xhtml+xml,application/xml;q=0.9,*/*;q=0.8", "Accept-Language": "en-us,en;q=0.5", "Sec-Fetch-Mode": "navigate", "User-Agent": "Mozilla/5.0 (Windows NT 10.0; Win64; x64) AppleWebKit/537.36 (KHTML, like Gecko) Chrome/92.0.4515.159 Safari/537.36"}, "language_preference": -1, "protocol": "https", "quality": 5.0, "resolution": "426x240", "source_preference": -1, "tbr": 134.375, "url": "https://rr2---sn-2gb7sn7y.googlevideo.com/videoplayback?expire=1735084295&ei=p_RqZ9D6CK7r6dsP4NDiUA&ip=78.80.167.40&id=o-AEZA9Rj-xdw0fNy3KwCQ_Rf8DsjbZe6x1dK42PAqwbFR&itag=242&aitags=133%2C134%2C135%2C136%2C137%2C160%2C242%2C243%2C244%2C247%2C248%2C278&source=youtube&requiressl=yes&xpc=EgVo2aDSNQ%3D%3D&met=1735062695%2C&mh=fL&mm=31%2C29&mn=sn-2gb7sn7y%2Csn-2gb7snez&ms=au%2Crdu&mv=m&mvi=2&pl=21&rms=au%2Cau&initcwndbps=2428750&siu=1&bui=AfMhrI8UUtfJFmlWA0P1NeAleRhYXtuSzltbcsSfL5zzFfhSrIIeB-HSk9S2WDsX36ct0863Fg&spc=x-caUPJUU24pl0MZR7CTDF7b4tCF-XKGiYd2whAttb0W6S_axAmkWjWbJ-P6Rm6ffg&vprv=1&svpuc=1&mime=video%2Fwebm&ns=nScaY93FuzSjzcW-gG5nYqIQ&rqh=1&gir=yes&clen=102713488&dur=6115.000&lmt=1710564448836657&mt=1735062329&fvip=1&keepalive=yes&fexp=51326932%2C51335594&c=WEB_CREATOR&sefc=1&txp=730F224&n=h4qEtGkeb2GfrQ&sparams=expire%2Cei%2Cip%2Cid%2Caitags%2Csource%2Crequiressl%2Cxpc%2Csiu%2Cbui%2Cspc%2Cvprv%2Csvpuc%2Cmime%2Cns%2Crqh%2Cgir%2Cclen%2Cdur%2Clmt&lsparams=met%2Cmh%2Cmm%2Cmn%2Cms%2Cmv%2Cmvi%2Cpl%2Crms%2Cinitcwndbps&lsig=AGluJ3MwRQIgcKFmRA9PckzcKOKwkhfqjAA76g3SxGGB44ThN7t-VRwCIQCDP7ZVJmBAVdsWitPfyMoUzwubCXIdBKwiKuuWN0D_QQ%3D%3D&sig=AJfQdSswRQIhAPrOJCQgOFSUivefkGfywEAXWi7uC6TMiEMAJYsrAAFZAiBIe4jX8NUhZS2FOvrrn4E4zAcaQvCexzoSMvlNBlDfzA%3D%3D", "vbr": 134.375, "vcodec": "vp9", "video_ext": "webm", "width": 426}, {"abr": 0, "acodec": "none", "aspect_ratio": 1.78, "audio_ext": "none", "container": "mp4_dash", "downloader_options": {"http_chunk_size": 10485760}, "dynamic_range": "SDR", "ext": "mp4", "filesize": 52973755, "filesize_approx": 52973480, "format": "160 - 256x144 (144p)", "format_id": "160", "format_note": "144p", "fps": 30, "has_drm": false, "height": 144, "http_headers": {"Accept": "text/html,application/xhtml+xml,application/xml;q=0.9,*/*;q=0.8", "Accept-Language": "en-us,en;q=0.5", "Sec-Fetch-Mode": "navigate", "User-Agent": "Mozilla/5.0 (Windows NT 10.0; Win64; x64) AppleWebKit/537.36 (KHTML, like Gecko) Chrome/92.0.4515.159 Safari/537.36"}, "language_preference": -1, "protocol": "https", "quality": 0.0, "resolution": "256x144", "source_preference": -1, "tbr": 69.303, "url": "https://rr2---sn-2gb7sn7y.googlevideo.com/videoplayback?expire=1735084295&ei=p_RqZ9D6CK7r6dsP4NDiUA&ip=78.80.167.40&id=o-AEZA9Rj-xdw0fNy3KwCQ_Rf8DsjbZe6x1dK42PAqwbFR&itag=160&aitags=133%2C134%2C135%2C136%2C137%2C160%2C242%2C243%2C244%2C247%2C248%2C278&source=youtube&requiressl=yes&xpc=EgVo2aDSNQ%3D%3D&met=1735062695%2C&mh=fL&mm=31%2C29&mn=sn-2gb7sn7y%2Csn-2gb7snez&ms=au%2Crdu&mv=m&mvi=2&pl=21&rms=au%2Cau&initcwndbps=2428750&siu=1&bui=AfMhrI8UUtfJFmlWA0P1NeAleRhYXtuSzltbcsSfL5zzFfhSrIIeB-HSk9S2WDsX36ct0863Fg&spc=x-caUPJUU24pl0MZR7CTDF7b4tCF-XKGiYd2whAttb0W6S_axAmkWjWbJ-P6Rm6ffg&vprv=1&svpuc=1&mime=video%2Fmp4&ns=nScaY93FuzSjzcW-gG5nYqIQ&rqh=1&gir=yes&clen=52973755&dur=6115.000&lmt=1710564434548430&mt=1735062329&fvip=1&keepalive=yes&fexp=51326932%2C51335594&c=WEB_CREATOR&sefc=1&txp=7309224&n=h4qEtGkeb2GfrQ&sparams=expire%2Cei%2Cip%2Cid%2Caitags%2Csource%2Crequiressl%2Cxpc%2Csiu%2Cbui%2Cspc%2Cvprv%2Csvpuc%2Cmime%2Cns%2Crqh%2Cgir%2Cclen%2Cdur%2Clmt&lsparams=met%2Cmh%2Cmm%2Cmn%2Cms%2Cmv%2Cmvi%2Cpl%2Crms%2Cinitcwndbps&lsig=AGluJ3MwRQIgcKFmRA9PckzcKOKwkhfqjAA76g3SxGGB44ThN7t-VRwCIQCDP7ZVJmBAVdsWitPfyMoUzwubCXIdBKwiKuuWN0D_QQ%3D%3D&sig=AJfQdSswRQIgDZxFOecYtEWFqfFNAJaFytfxNQQt8-C_GpkjzRGAp1cCIQC2nqz5-jqFsyQv2yO7vnC-J49pI7Bx5PkM-hxCzmgADA%3D%3D", "vbr": 69.303, "vcodec": "avc1.4d400c", "video_ext": "mp4", "width": 256}, {"abr": 0, "acodec": "none", "aspect_ratio": 1.78, "audio_ext": "none", "container": "webm_dash", "downloader_options": {"http_chunk_size": 10485760}, "dynamic_range": "SDR", "ext": "webm", "filesize": 49193110, "filesize_approx": 49192881, "format": "278 - 256x144 (144p)", "format_id": "278", "format_note": "144p", "fps": 30, "has_drm": false, "height": 144, "http_headers": {"Accept": "text/html,application/xhtml+xml,application/xml;q=0.9,*/*;q=0.8", "Accept-Language": "en-us,en;q=0.5", "Sec-Fetch-Mode": "navigate", "User-Agent": "Mozilla/5.0 (Windows NT 10.0; Win64; x64) AppleWebKit/537.36 (KHTML, like Gecko) Chrome/92.0.4515.159 Safari/537.36"}, "language_preference": -1, "protocol": "https", "quality": 0.0, "resolution": "256x144", "source_preference": -1, "tbr": 64.357, "url": "https://rr2---sn-2gb7sn7y.googlevideo.com/videoplayback?expire=1735084295&ei=p_RqZ9D6CK7r6dsP4NDiUA&ip=78.80.167.40&id=o-AEZA9Rj-xdw0fNy3KwCQ_Rf8DsjbZe6x1dK42PAqwbFR&itag=278&aitags=133%2C134%2C135%2C136%2C137%2C160%2C242%2C243%2C244%2C247%2C248%2C278&source=youtube&requiressl=yes&xpc=EgVo2aDSNQ%3D%3D&met=1735062695%2C&mh=fL&mm=31%2C29&mn=sn-2gb7sn7y%2Csn-2gb7snez&ms=au%2Crdu&mv=m&mvi=2&pl=21&rms=au%2Cau&initcwndbps=2428750&siu=1&bui=AfMhrI8UUtfJFmlWA0P1NeAleRhYXtuSzltbcsSfL5zzFfhSrIIeB-HSk9S2WDsX36ct0863Fg&spc=x-caUPJUU24pl0MZR7CTDF7b4tCF-XKGiYd2whAttb0W6S_axAmkWjWbJ-P6Rm6ffg&vprv=1&svpuc=1&mime=video%2Fwebm&ns=nScaY93FuzSjzcW-gG5nYqIQ&rqh=1&gir=yes&clen=49193110&dur=6115.000&lmt=1710564446258537&mt=1735062329&fvip=1&keepalive=yes&fexp=51326932%2C51335594&c=WEB_CREATOR&sefc=1&txp=730F224&n=h4qEtGkeb2GfrQ&sparams=expire%2Cei%2Cip%2Cid%2Caitags%2Csource%2Crequiressl%2Cxpc%2Csiu%2Cbui%2Cspc%2Cvprv%2Csvpuc%2Cmime%2Cns%2Crqh%2Cgir%2Cclen%2Cdur%2Clmt&lsparams=met%2Cmh%2Cmm%2Cmn%2Cms%2Cmv%2Cmvi%2Cpl%2Crms%2Cinitcwndbps&lsig=AGluJ3MwRQIgcKFmRA9PckzcKOKwkhfqjAA76g3SxGGB44ThN7t-VRwCIQCDP7ZVJmBAVdsWitPfyMoUzwubCXIdBKwiKuuWN0D_QQ%3D%3D&sig=AJfQdSswRQIhAKWIRfT3OUxzLgS18Xeo30OCAIdZih-9TfN2FbnkNYnKAiBoPjDgOaBmKp8E9yzDdOnRLnjIzdt7immGWeH7HDLhbg%3D%3D", "vbr": 64.357, "vcodec": "vp9", "video_ext": "webm", "width": 256}, {"abr": 0, "acodec": "none", "aspect_ratio": 1.78, "audio_ext": "none", "container": "webm_dash", "downloader_options": {"http_chunk_size": 10485760}, "dynamic_range": "SDR", "ext": "webm", "filesize": 25673301, "filesize_approx": 25673058, "format": "598 - 256x144 (144p)", "format_id": "598", "format_note": "144p", "fps": 15, "has_drm": false, "height": 144, "http_headers": {"Accept": "text/html,application/xhtml+xml,application/xml;q=0.9,*/*;q=0.8", "Accept-Language": "en-us,en;q=0.5", "Sec-Fetch-Mode": "navigate", "User-Agent": "Mozilla/5.0 (Windows NT 10.0; Win64; x64) AppleWebKit/537.36 (KHTML, like Gecko) Chrome/92.0.4515.159 Safari/537.36"}, "language_preference": -1, "protocol": "https", "quality": 0.0, "resolution": "256x144", "source_preference": -1, "tbr": 33.587, "url": "https://rr1---sn-2gb7snez.googlevideo.com/videoplayback?expire=1735084295&ei=p_RqZ6igEeTi6dsPi77KyQU&ip=78.80.167.40&id=o-AC0wiWbzedkChxzzacgW8yzNWR9XAImmR4Ttl_SH-ynR&itag=598&aitags=133%2C134%2C135%2C136%2C137%2C160%2C242%2C243%2C244%2C247%2C248%2C278%2C597%2C598&source=youtube&requiressl=yes&xpc=EgVo2aDSNQ%3D%3D&met=1735062695%2C&mh=fL&mm=31%2C26&mn=sn-2gb7snez%2Csn-c0q7lnz7&ms=au%2Conr&mv=m&mvi=1&pl=21&rms=au%2Cau&initcwndbps=2288750&siu=1&bui=AfMhrI9B8C1ad2TEjuVUQXvRcJuys5dij3TafRBWz6__IXVnVooMPRSXQK6K88JQyoodqwxzjw&vprv=1&svpuc=1&mime=video%2Fwebm&ns=V37ev8fvNAZwHt8_Ko58tW4Q&rqh=1&gir=yes&clen=25673301&dur=6114.999&lmt=1710564445470436&mt=1735062329&fvip=2&keepalive=yes&fexp=51326932%2C51331020%2C51335594&c=MWEB&sefc=1&txp=730F224&n=l-9iOvVIChTUpQ&sparams=expire%2Cei%2Cip%2Cid%2Caitags%2Csource%2Crequiressl%2Cxpc%2Csiu%2Cbui%2Cvprv%2Csvpuc%2Cmime%2Cns%2Crqh%2Cgir%2Cclen%2Cdur%2Clmt&lsparams=met%2Cmh%2Cmm%2Cmn%2Cms%2Cmv%2Cmvi%2Cpl%2Crms%2Cinitcwndbps&lsig=AGluJ3MwRQIhAN7qMZex9PfxvHburkPwnYwaKqOIfNgDcg9FzZ5Jm2siAiACAIqbMEJ5YX6D0euX5WpM2GKq3_X-wEk2UaExPZ7_YQ%3D%3D&sig=AJfQdSswRQIgPpLkjoyCIF6i2L8F6u9f6obU0GjdQcSz84f6dzLKR80CIQDA3wPDP6vJ_1vZfMdv41qf6d32Sz73MD2pVT_fiQFaeA%3D%3D", "vbr": 33.587, "vcodec": "vp9", "video_ext": "webm", "width": 256}, {"abr": 0, "acodec": "none", "aspect_ratio": 1.78, "audio_ext": "none", "container": "mp4_dash", "downloader_options": {"http_chunk_size": 10485760}, "dynamic_range": "SDR", "ext": "mp4", "filesize": 25329834, "filesize_approx": 25329094, "format": "597 - 256x144 (144p)", "format_id": "597", "format_note": "144p", "fps": 15, "has_drm": false, "height": 144, "http_headers": {"Accept": "text/html,application/xhtml+xml,application/xml;q=0.9,*/*;q=0.8", "Accept-Language": "en-us,en;q=0.5", "Sec-Fetch-Mode": "navigate", "User-Agent": "Mozilla/5.0 (Windows NT 10.0; Win64; x64) AppleWebKit/537.36 (KHTML, like Gecko) Chrome/92.0.4515.159 Safari/537.36"}, "language_preference": -1, "protocol": "https", "quality": 0.0, "resolution": "256x144", "source_preference": -1, "tbr": 33.137, "url": "https://rr1---sn-2gb7snez.googlevideo.com/videoplayback?expire=1735084295&ei=p_RqZ6igEeTi6dsPi77KyQU&ip=78.80.167.40&id=o-AC0wiWbzedkChxzzacgW8yzNWR9XAImmR4Ttl_SH-ynR&itag=597&aitags=133%2C134%2C135%2C136%2C137%2C160%2C242%2C243%2C244%2C247%2C248%2C278%2C597%2C598&source=youtube&requiressl=yes&xpc=EgVo2aDSNQ%3D%3D&met=1735062695%2C&mh=fL&mm=31%2C26&mn=sn-2gb7snez%2Csn-c0q7lnz7&ms=au%2Conr&mv=m&mvi=1&pl=21&rms=au%2Cau&initcwndbps=2288750&siu=1&bui=AfMhrI9B8C1ad2TEjuVUQXvRcJuys5dij3TafRBWz6__IXVnVooMPRSXQK6K88JQyoodqwxzjw&vprv=1&svpuc=1&mime=video%2Fmp4&ns=V37ev8fvNAZwHt8_Ko58tW4Q&rqh=1&gir=yes&clen=25329834&dur=6115.000&lmt=1710564441273091&mt=1735062329&fvip=2&keepalive=yes&fexp=51326932%2C51331020%2C51335594&c=MWEB&sefc=1&txp=7309224&n=l-9iOvVIChTUpQ&sparams=expire%2Cei%2Cip%2Cid%2Caitags%2Csource%2Crequiressl%2Cxpc%2Csiu%2Cbui%2Cvprv%2Csvpuc%2Cmime%2Cns%2Crqh%2Cgir%2Cclen%2Cdur%2Clmt&lsparams=met%2Cmh%2Cmm%2Cmn%2Cms%2Cmv%2Cmvi%2Cpl%2Crms%2Cinitcwndbps&lsig=AGluJ3MwRQIhAN7qMZex9PfxvHburkPwnYwaKqOIfNgDcg9FzZ5Jm2siAiACAIqbMEJ5YX6D0euX5WpM2GKq3_X-wEk2UaExPZ7_YQ%3D%3D&sig=AJfQdSswRAIgEs1a6yT2erL4tr3uhE_ZoD9S1n2ba2bMJNVdpGHILbACICgjH5zcbjigukgXqEi7IW92allMtPlNB1xKzLUGMZbU", "vbr": 33.137, "vcodec": "avc1.4d400b", "video_ext": "mp4", "width": 256}], "fulltitle": "\u3010#hololivefesEXPO24_DAY1\u3011hololive 5th fes. Capture the Moment hololive stage1 DAY1\u3010\u30c1\u30e9\u898b\u305b\u3011", "has_drm": false, "heatmap": [{"end_time": 61.15, "start_time": 0.0, "value": 0.1133269469394111}, {"end_time": 122.3, "start_time": 61.15, "value": 0.1410302958182779}, {"end_time": 183.45, "start_time": 122.3, "value": 0.07144546045969768}, {"end_time": 244.6, "start_time": 183.45, "value": 0.0579635631158255}, {"end_time": 305.75, "start_time": 244.6, "value": 0.055712876326013835}, {"end_time": 366.9, "start_time": 305.75, "value": 0.04036251775529016}, {"end_time": 428.05, "start_time": 366.9, "value": 0.038036745279903514}, {"end_time": 489.2, "start_time": 428.05, "value": 0.03550757662891845}, {"end_time": 550.35, "start_time": 489.2, "value": 0.030855785686589702}, {"end_time": 611.5, "start_time": 550.35, "value": 0.04083047137533021}, {"end_time": 672.65, "start_time": 611.5, "value": 0.042874564099322394}, {"end_time": 733.8, "start_time": 672.65, "value": 0.05049240469514372}, {"end_time": 794.95, "start_time": 733.8, "value": 0.03567666992945334}, {"end_time": 856.1, "start_time": 794.95, "value": 0.04527145402808663}, {"end_time": 917.25, "start_time": 856.1, "value": 0.27124183447619876}, {"end_time": 978.4, "start_time": 917.25, "value": 0.25471578515997356}, {"end_time": 1039.55, "start_time": 978.4, "value": 0.10245853508889091}, {"end_time": 1100.7, "start_time": 1039.55, "value": 0.036779372391063325}, {"end_time": 1161.85, "start_time": 1100.7, "value": 0.04299056853811054}, {"end_time": 1223.0, "start_time": 1161.85, "value": 0.025399291631711996}, {"end_time": 1284.15, "start_time": 1223.0, "value": 0.044430085226849284}, {"end_time": 1345.3, "start_time": 1284.15, "value": 0.02809460815802834}, {"end_time": 1406.45, "start_time": 1345.3, "value": 0.03962981896041088}, {"end_time": 1467.6, "start_time": 1406.45, "value": 0.040415101687002}, {"end_time": 1528.75, "start_time": 1467.6, "value": 0.03471849398014159}, {"end_time": 1589.9, "start_time": 1528.75, "value": 0.03469833561951735}, {"end_time": 1651.05, "start_time": 1589.9, "value": 0.04365376824510871}, {"end_time": 1712.2, "start_time": 1651.05, "value": 0.042924552172777866}, {"end_time": 1773.35, "start_time": 1712.2, "value": 0.0699200150365575}, {"end_time": 1834.5, "start_time": 1773.35, "value": 0.2228017470385004}, {"end_time": 1895.65, "start_time": 1834.5, "value": 0.21704109089875104}, {"end_time": 1956.8, "start_time": 1895.65, "value": 0.21874081486547683}, {"end_time": 2017.95, "start_time": 1956.8, "value": 0.07803637693991651}, {"end_time": 2079.1, "start_time": 2017.95, "value": 0.05121108844482342}, {"end_time": 2140.25, "start_time": 2079.1, "value": 0.04670977312635798}, {"end_time": 2201.4, "start_time": 2140.25, "value": 0.0457201490987185}, {"end_time": 2262.55, "start_time": 2201.4, "value": 0.046714595855537513}, {"end_time": 2323.7, "start_time": 2262.55, "value": 0.03991744134990844}, {"end_time": 2384.85, "start_time": 2323.7, "value": 0.04144506832973789}, {"end_time": 2446.0, "start_time": 2384.85, "value": 0.038423884200511016}, {"end_time": 2507.15, "start_time": 2446.0, "value": 0.048477662647795815}, {"end_time": 2568.3, "start_time": 2507.15, "value": 0.04007615121741787}, {"end_time": 2629.45, "start_time": 2568.3, "value": 0.06951493167932496}, {"end_time": 2690.6, "start_time": 2629.45, "value": 0.055317017652111264}, {"end_time": 2751.75, "start_time": 2690.6, "value": 0.04316419973549758}, {"end_time": 2812.9, "start_time": 2751.75, "value": 0.04814343780546143}, {"end_time": 2874.05, "start_time": 2812.9, "value": 0.05381306412276442}, {"end_time": 2935.2, "start_time": 2874.05, "value": 0.049805855210762244}, {"end_time": 2996.35, "start_time": 2935.2, "value": 0.04054382000513054}, {"end_time": 3057.5, "start_time": 2996.35, "value": 0.04733603525926434}, {"end_time": 3118.65, "start_time": 3057.5, "value": 0.056746610523625556}, {"end_time": 3179.8, "start_time": 3118.65, "value": 0.046182665010690356}, {"end_time": 3240.95, "start_time": 3179.8, "value": 0.05190736106910778}, {"end_time": 3302.1, "start_time": 3240.95, "value": 0.06748297669655642}, {"end_time": 3363.25, "start_time": 3302.1, "value": 0.05453023308233941}, {"end_time": 3424.4, "start_time": 3363.25, "value": 0.0597742551679144}, {"end_time": 3485.55, "start_time": 3424.4, "value": 0.09998089519531397}, {"end_time": 3546.7, "start_time": 3485.55, "value": 0.0837326739206016}, {"end_time": 3607.85, "start_time": 3546.7, "value": 0.0755777560776543}, {"end_time": 3669.0, "start_time": 3607.85, "value": 0.08364361203059896}, {"end_time": 3730.15, "start_time": 3669.0, "value": 0.3494004724559128}, {"end_time": 3791.3, "start_time": 3730.15, "value": 0.5291088782738138}, {"end_time": 3852.45, "start_time": 3791.3, "value": 0.4202546630814692}, {"end_time": 3913.6, "start_time": 3852.45, "value": 0.49159024623414843}, {"end_time": 3974.75, "start_time": 3913.6, "value": 0.3846320821636394}, {"end_time": 4035.9, "start_time": 3974.75, "value": 0.6423414324272768}, {"end_time": 4097.05, "start_time": 4035.9, "value": 0.6278714323193318}, {"end_time": 4158.2, "start_time": 4097.05, "value": 0.44638569867241756}, {"end_time": 4219.35, "start_time": 4158.2, "value": 0.4030065120276357}, {"end_time": 4280.5, "start_time": 4219.35, "value": 0.3185819771470932}, {"end_time": 4341.65, "start_time": 4280.5, "value": 0.40220545994764684}, {"end_time": 4402.8, "start_time": 4341.65, "value": 1.0}, {"end_time": 4463.95, "start_time": 4402.8, "value": 0.4874112899021972}, {"end_time": 4525.1, "start_time": 4463.95, "value": 0.4856120817716713}, {"end_time": 4586.25, "start_time": 4525.1, "value": 0.46808852375110777}, {"end_time": 4647.4, "start_time": 4586.25, "value": 0.36529836291486983}, {"end_time": 4708.55, "start_time": 4647.4, "value": 0.22730422110666132}, {"end_time": 4769.7, "start_time": 4708.55, "value": 0.34186111611320913}, {"end_time": 4830.85, "start_time": 4769.7, "value": 0.4354951605288294}, {"end_time": 4892.0, "start_time": 4830.85, "value": 0.24677119009694964}, {"end_time": 4953.15, "start_time": 4892.0, "value": 0.35085837377669166}, {"end_time": 5014.3, "start_time": 4953.15, "value": 0.18653438341302245}, {"end_time": 5075.45, "start_time": 5014.3, "value": 0.25138192634336354}, {"end_time": 5136.6, "start_time": 5075.45, "value": 0.6474368238256545}, {"end_time": 5197.75, "start_time": 5136.6, "value": 0.48068500038492823}, {"end_time": 5258.9, "start_time": 5197.75, "value": 0.8131674456911738}, {"end_time": 5320.05, "start_time": 5258.9, "value": 0.595504433115778}, {"end_time": 5381.2, "start_time": 5320.05, "value": 0.7353136041956061}, {"end_time": 5442.35, "start_time": 5381.2, "value": 0.6620178049658866}, {"end_time": 5503.5, "start_time": 5442.35, "value": 0.3267543862843265}, {"end_time": 5564.65, "start_time": 5503.5, "value": 0.25244385894138605}, {"end_time": 5625.8, "start_time": 5564.65, "value": 0.12932548678532554}, {"end_time": 5686.95, "start_time": 5625.8, "value": 0.21661700145712776}, {"end_time": 5748.1, "start_time": 5686.95, "value": 0.1856605437264636}, {"end_time": 5809.25, "start_time": 5748.1, "value": 0.3205841412578024}, {"end_time": 5870.4, "start_time": 5809.25, "value": 0.05593725946537069}, {"end_time": 5931.55, "start_time": 5870.4, "value": 0.018318716013414244}, {"end_time": 5992.7, "start_time": 5931.55, "value": 0.011866406064507498}, {"end_time": 6053.85, "start_time": 5992.7, "value": 0.0}, {"end_time": 6115.0, "start_time": 6053.85, "value": 0.017056306771148992}], "http_headers": {"Accept": "text/html,application/xhtml+xml,application/xml;q=0.9,*/*;q=0.8", "Accept-Language": "en-us,en;q=0.5", "Sec-Fetch-Mode": "navigate", "User-Agent": "Mozilla/5.0 (Windows NT 10.0; Win64; x64) AppleWebKit/537.36 (KHTML, like Gecko) Chrome/92.0.4515.159 Safari/537.36"}, "id": "00xeNL3vdQo", "is_live": false, "language_preference": -1, "like_count": 48671, "live_status": "was_live", "playable_in_embed": true, "protocol": "https", "quality": 1.0, "release_date": "20240316", "release_timestamp": 1710558017, "release_year": 2024, "resolution": "audio only", "source_preference": -1, "subtitles": {"live_chat": [{"ext": "json", "protocol": "youtube_live_chat_replay", "url": "https://www.youtube.com/watch?v=00xeNL3vdQo&bpctr=9999999999&has_verified=1", "video_id": "00xeNL3vdQo"}]}, "tags": ["hololive", "\u30db\u30ed\u30e9\u30a4\u30d6", "VTuber", "\u30d0\u30fc\u30c1\u30e3\u30ebYouTuber", "VR"], "tbr": 30.783, "thumbnail": "https://i.ytimg.com/vi/00xeNL3vdQo/maxresdefault.jpg", "thumbnails": [{"id": "0", "preference": -37, "url": "https://i.ytimg.com/vi/00xeNL3vdQo/3.jpg"}, {"id": "1", "preference": -36, "url": "https://i.ytimg.com/vi_webp/00xeNL3vdQo/3.webp"}, {"id": "2", "preference": -35, "url": "https://i.ytimg.com/vi/00xeNL3vdQo/2.jpg"}, {"id": "3", "preference": -34, "url": "https://i.ytimg.com/vi_webp/00xeNL3vdQo/2.webp"}, {"id": "4", "preference": -33, "url": "https://i.ytimg.com/vi/00xeNL3vdQo/1.jpg"}, {"id": "5", "preference": -32, "url": "https://i.ytimg.com/vi_webp/00xeNL3vdQo/1.webp"}, {"id": "6", "preference": -31, "url": "https://i.ytimg.com/vi/00xeNL3vdQo/mq3.jpg"}, {"id": "7", "preference": -30, "url": "https://i.ytimg.com/vi_webp/00xeNL3vdQo/mq3.webp"}, {"id": "8", "preference": -29, "url": "https://i.ytimg.com/vi/00xeNL3vdQo/mq2.jpg"}, {"id": "9", "preference": -28, "url": "https://i.ytimg.com/vi_webp/00xeNL3vdQo/mq2.webp"}, {"id": "10", "preference": -27, "url": "https://i.ytimg.com/vi/00xeNL3vdQo/mq1.jpg"}, {"id": "11", "preference": -26, "url": "https://i.ytimg.com/vi_webp/00xeNL3vdQo/mq1.webp"}, {"id": "12", "preference": -25, "url": "https://i.ytimg.com/vi/00xeNL3vdQo/hq3.jpg"}, {"id": "13", "preference": -24, "url": "https://i.ytimg.com/vi_webp/00xeNL3vdQo/hq3.webp"}, {"id": "14", "preference": -23, "url": "https://i.ytimg.com/vi/00xeNL3vdQo/hq2.jpg"}, {"id": "15", "preference": -22, "url": "https://i.ytimg.com/vi_webp/00xeNL3vdQo/hq2.webp"}, {"id": "16", "preference": -21, "url": "https://i.ytimg.com/vi/00xeNL3vdQo/hq1.jpg"}, {"id": "17", "preference": -20, "url": "https://i.ytimg.com/vi_webp/00xeNL3vdQo/hq1.webp"}, {"id": "18", "preference": -19, "url": "https://i.ytimg.com/vi/00xeNL3vdQo/sd3.jpg"}, {"id": "19", "preference": -18, "url": "https://i.ytimg.com/vi_webp/00xeNL3vdQo/sd3.webp"}, {"id": "20", "preference": -17, "url": "https://i.ytimg.com/vi/00xeNL3vdQo/sd2.jpg"}, {"id": "21", "preference": -16, "url": "https://i.ytimg.com/vi_webp/00xeNL3vdQo/sd2.webp"}, {"id": "22", "preference": -15, "url": "https://i.ytimg.com/vi/00xeNL3vdQo/sd1.jpg"}, {"id": "23", "preference": -14, "url": "https://i.ytimg.com/vi_webp/00xeNL3vdQo/sd1.webp"}, {"id": "24", "preference": -13, "url": "https://i.ytimg.com/vi/00xeNL3vdQo/default.jpg"}, {"height": 90, "id": "25", "preference": -13, "resolution": "120x90", "url": "https://i.ytimg.com/vi/00xeNL3vdQo/default.jpg?v=65ef0a5f", "width": 120}, {"id": "26", "preference": -12, "url": "https://i.ytimg.com/vi_webp/00xeNL3vdQo/default.webp"}, {"id": "27", "preference": -11, "url": "https://i.ytimg.com/vi/00xeNL3vdQo/mqdefault.jpg"}, {"height": 180, "id": "28", "preference": -11, "resolution": "320x180", "url": "https://i.ytimg.com/vi/00xeNL3vdQo/mqdefault.jpg?v=65ef0a5f", "width": 320}, {"id": "29", "preference": -10, "url": "https://i.ytimg.com/vi_webp/00xeNL3vdQo/mqdefault.webp"}, {"id": "30", "preference": -9, "url": "https://i.ytimg.com/vi/00xeNL3vdQo/0.jpg"}, {"id": "31", "preference": -8, "url": "https://i.ytimg.com/vi_webp/00xeNL3vdQo/0.webp"}, {"id": "32", "preference": -7, "url": "https://i.ytimg.com/vi/00xeNL3vdQo/hqdefault.jpg"}, {"height": 94, "id": "33", "preference": -7, "resolution": "168x94", "url": "https://i.ytimg.com/vi/00xeNL3vdQo/hqdefault.jpg?sqp=-oaymwEbCKgBEF5IVfKriqkDDggBFQAAiEIYAXABwAEG&rs=AOn4CLB5Vc29hnE2njSy5yj8vKzPb6tVbw", "width": 168}, {"height": 110, "id": "34", "preference": -7, "resolution": "196x110", "url": "https://i.ytimg.com/vi/00xeNL3vdQo/hqdefault.jpg?sqp=-oaymwEbCMQBEG5IVfKriqkDDggBFQAAiEIYAXABwAEG&rs=AOn4CLA3KJfpmNTDJLGyqR05jhys3tHf7A", "width": 196}, {"height": 138, "id": "35", "preference": -7, "resolution": "246x138", "url": "https://i.ytimg.com/vi/00xeNL3vdQo/hqdefault.jpg?sqp=-oaymwEcCPYBEIoBSFXyq4qpAw4IARUAAIhCGAFwAcABBg==&rs=AOn4CLA_fyG3VmeatLUCTVWK-QJiq2Qgsw", "width": 246}, {"height": 188, "id": "36", "preference": -7, "resolution": "336x188", "url": "https://i.ytimg.com/vi/00xeNL3vdQo/hqdefault.jpg?sqp=-oaymwEcCNACELwBSFXyq4qpAw4IARUAAIhCGAFwAcABBg==&rs=AOn4CLBO5k7y8lQ73Fg42jN3imOET4zkmw", "width": 336}, {"height": 360, "id": "37", "preference": -7, "resolution": "480x360", "url": "https://i.ytimg.com/vi/00xeNL3vdQo/hqdefault.jpg?v=65ef0a5f", "width": 480}, {"id": "38", "preference": -6, "url": "https://i.ytimg.com/vi_webp/00xeNL3vdQo/hqdefault.webp"}, {"id": "39", "preference": -5, "url": "https://i.ytimg.com/vi/00xeNL3vdQo/sddefault.jpg"}, {"height": 480, "id": "40", "preference": -5, "resolution": "640x480", "url": "https://i.ytimg.com/vi/00xeNL3vdQo/sddefault.jpg?v=65ef0a5f", "width": 640}, {"id": "41", "preference": -4, "url": "https://i.ytimg.com/vi_webp/00xeNL3vdQo/sddefault.webp"}, {"id": "42", "preference": -3, "url": "https://i.ytimg.com/vi/00xeNL3vdQo/hq720.jpg"}, {"height": 386, "id": "43", "preference": -3, "resolution": "686x386", "url": "https://i.ytimg.com/vi/00xeNL3vdQo/hq720.jpg?sqp=-oaymwEhCK4FEIIDSFryq4qpAxMIARUAAAAAGAElAADIQj0AgKJD&rs=AOn4CLA1zTOmOgp_JFRvlUXJ3t8vcxNZ8g", "width": 686}, {"id": "44", "preference": -2, "url": "https://i.ytimg.com/vi_webp/00xeNL3vdQo/hq720.webp"}, {"height": 1080, "id": "45", "preference": -1, "resolution": "1920x1080", "url": "https://i.ytimg.com/vi/00xeNL3vdQo/maxresdefault.jpg", "width": 1920}, {"id": "46", "preference": 0, "url": "https://i.ytimg.com/vi_webp/00xeNL3vdQo/maxresdefault.webp"}], "timestamp": 1710564423, "title": "\u3010#hololivefesEXPO24_DAY1\u3011hololive 5th fes. Capture the Moment hololive stage1 DAY1\u3010\u30c1\u30e9\u898b\u305b\u3011", "upload_date": "20240316", "uploader": "hololive \u30db\u30ed\u30e9\u30a4\u30d6 - VTuber Group", "uploader_id": "@hololive", "uploader_url": "https://www.youtube.com/@hololive", "url": "https://rr1---sn-2gb7snez.googlevideo.com/videoplayback?expire=1735084295&ei=p_RqZ6igEeTi6dsPi77KyQU&ip=78.80.167.40&id=o-AC0wiWbzedkChxzzacgW8yzNWR9XAImmR4Ttl_SH-ynR&itag=599&source=youtube&requiressl=yes&xpc=EgVo2aDSNQ%3D%3D&met=1735062695%2C&mh=fL&mm=31%2C26&mn=sn-2gb7snez%2Csn-c0q7lnz7&ms=au%2Conr&mv=m&mvi=1&pl=21&rms=au%2Cau&initcwndbps=2288750&siu=1&bui=AfMhrI9B8C1ad2TEjuVUQXvRcJuys5dij3TafRBWz6__IXVnVooMPRSXQK6K88JQyoodqwxzjw&vprv=1&svpuc=1&mime=audio%2Fmp4&ns=V37ev8fvNAZwHt8_Ko58tW4Q&rqh=1&gir=yes&clen=23530782&dur=6115.160&lmt=1710564444576966&mt=1735062329&fvip=2&keepalive=yes&fexp=51326932%2C51331020%2C51335594&c=MWEB&sefc=1&txp=7308224&n=l-9iOvVIChTUpQ&sparams=expire%2Cei%2Cip%2Cid%2Citag%2Csource%2Crequiressl%2Cxpc%2Csiu%2Cbui%2Cvprv%2Csvpuc%2Cmime%2Cns%2Crqh%2Cgir%2Cclen%2Cdur%2Clmt&lsparams=met%2Cmh%2Cmm%2Cmn%2Cms%2Cmv%2Cmvi%2Cpl%2Crms%2Cinitcwndbps&lsig=AGluJ3MwRQIhAN7qMZex9PfxvHburkPwnYwaKqOIfNgDcg9FzZ5Jm2siAiACAIqbMEJ5YX6D0euX5WpM2GKq3_X-wEk2UaExPZ7_YQ%3D%3D&sig=AJfQdSswRQIgK2h0G3NuoDGqenkVWbBI6Jt4vm6ObOdUAxgFLAWSxPECIQCoAw3wWt8a7SwzW2fZ9oZOhy_xxkmrkqjHaWr-3MJWyg%3D%3D", "vbr": 0, "vcodec": "none", "video_ext": "none", "view_count": 1257959, "was_live": true, "webpage_url": "https://www.youtube.com/watch?v=00xeNL3vdQo", "webpage_url_basename": "watch", "webpage_url_domain": "youtube.com"}