{"_format_sort_fields": ["quality", "res", "fps", "hdr:12", "source", "vcodec", "channels", "acodec", "lang", "proto"], "_type": "video", "_version": {"release_git_head": "197d0b03b6a3c8fe4fa5ace630eeffec629bf72c", "repository": "yt-dlp/yt-dlp", "version": "2024.11.04"}, "abr": 121.734, "acodec": "opus", "age_limit": 0, "aspect_ratio": 1.78, "asr": 48000, "audio_channels": 2, "availability": "public", "categories": ["Music"], "channel": "hololive English", "channel_follower_count": 797000, "channel_id": "UCotXwY6s8pWmuWd_snKYjhg", "channel_url": "https://www.youtube.com/channel/UCotXwY6s8pWmuWd_snKYjhg", "comment_count": 197, "description": "------------------------------\n\ud83c\udf89Blu-ray Pre-Order\ud83c\udf89\n\"hololive English 1st Concert -Connect the World-\" Blu-ray Pre-Order starts at 12.00PM Noon 11/30 JST!\ud83d\udcc0\n\nRelive the memories of the first ever hololive English live concert in North America \ud83d\udc40\u2728\n\n\ud83d\udd3dDetails\ud83d\udd3d\nhttps://shop.hololivepro.com/en/products/hololiveen_1stconcert_bluray\n\n#holoENConnect\n------------------------------\n\nA group of hololive English talents gather to relive their favorite moments from the \"hololive English 1st Concert -Connect the World-\", and perhaps even bring us some special news...?!\n\n[Participating talents]\n\u25b6Takanashi Kiara\n@TakanashiKiara \nhttps://twitter.com/takanashikiara\n\n\u25b6Mori Calliope\n@MoriCalliope \nhttps://twitter.com/moricalliope\n\n\u25b6IRyS\n@IRyS \nhttps://twitter.com/irys_en\n\n\u25b6FUWAMOCO\n@FUWAMOCOch \nhttps://twitter.com/fuwamoco_en\n\nFollow the official hololive English accounts!\n\u25b6Official YouTube channel: @hololiveEnglish \n\u25b6Official Twitter: https://twitter.com/hololivepro_EN\n\u25b6Official Facebook: https://www.facebook.com/hololivetv/\n\u25b6\ufe0fOfficial Reddit: https://www.reddit.com/r/Hololive/\n\n\u25b6Request from hololive production to underage viewers:\nPlease be sure to check the link below before viewing our content.\nhttps://en.hololive.tv/request-to-minors", "display_id": "gyjxee8NdTw", "duration": 2292, "duration_string": "38:12", "dynamic_range": "SDR", "epoch": 1732751476, "ext": "webm", "extractor": "youtube", "extractor_key": "Youtube", "filesize_approx": 987936099, "format": "399 - 1920x1080 (1080p60)+251 - audio only (medium)", "format_id": "399+251", "format_note": "1080p60+medium", "fps": 60, "fulltitle": "[Announcement] Favorite Moments From #holoENConnect ! With Special News Too...?!", "height": 1080, "id": "gyjxee8NdTw", "is_live": false, "language": "en", "like_count": 11206, "live_status": "not_live", "playable_in_embed": true, "protocol": "https+https", "release_date": "20231130", "release_timestamp": 1701310808, "release_year": 2023, "resolution": "1920x1080", "tags": [], "tbr": 3448.584, "thumbnail": "https://i.ytimg.com/vi/gyjxee8NdTw/maxresdefault.jpg", "timestamp": 1701310808, "title": "[Announcement] Favorite Moments From #holoENConnect ! With Special News Too...?!", "upload_date": "20231130", "uploader": "hololive English", "uploader_id": "@hololiveEnglish", "uploader_url": "https://www.youtube.com/@hololiveEnglish", "vbr": 3326.85, "vcodec": "av01.0.09M.08", "view_count": 109242, "was_live": false, "webpage_url": "https://www.youtube.com/watch?v=gyjxee8NdTw", "webpage_url_basename": "watch", "webpage_url_domain": "youtube.com", "width": 1920}