{"_format_sort_fields": ["quality", "res", "fps", "hdr:12", "source", "vcodec", "channels", "acodec", "lang", "proto"], "_type": "video", "_version": {"release_git_head": "4bd2655398aed450456197a6767639114a24eac2", "repository": "yt-dlp/yt-dlp", "version": "2024.12.06"}, "abr": 129.471, "acodec": "mp4a.40.2", "age_limit": 0, "asr": 44100, "audio_channels": 2, "audio_ext": "m4a", "availability": "subscriber_only", "categories": ["Entertainment"], "channel": "Takanashi Kiara Ch. hololive-EN", "channel_follower_count": 1560000, "channel_id": "UCHsx4Hqa-1ORjQTh9TYDhww", "channel_is_verified": true, "channel_url": "https://www.youtube.com/channel/UCHsx4Hqa-1ORjQTh9TYDhww", "comment_count": 62, "container": "m4a_dash", "description": "\ud83d\udc83 Takanashi Kiara - Fever Night \ud83d\udc83\nMV: https://youtu.be/SF4rteXN57w\nStreaming: https://cover.lnk.to/FeverNight\n\n\n\u2728 Takanashi Kiara - SPARKS \u2728\nMV: https://youtu.be/Lq9eqHDKJPE\nStreaming: https://kiara.streamlink.to/SPARKS\n\n\n\ud83d\udc96 Takanashi Kiara - Heart Challenger \ud83d\udc96\nMV: https://youtu.be/KpSLiHAYe7k\nStreaming: https://kiara.streamlink.to/HeartChallenger\n\n\n\ud83d\udd25 Takanashi Kiara's - HINOTORI \ud83d\udd25\nMV: https://youtu.be/eDfMDkgheQY\nStreaming: https://kiara.streamlink.to/hinotori\n\n \ud83c\udff5\ufe0f[Twitter] \ud83c\udff5\ufe0f\nhttps://twitter.com/takanashikiara\n\n \ud83c\udff5\ufe0f[Hashtags] \ud83c\udff5\ufe0f\n#kfp #\u30ad\u30a2\u30e9\u30a4\u30d6#hololiveenglish #holomyth #takanashikiara \nFANART #artsofashes #\u7d75\u30cb\u30c3\u30af\u30b9 \n\n\n\uff1d\uff1d\uff1d\uff1d\uff1d\uff1d\uff1d\uff1d\uff1d\uff1d\uff1d\uff1d\uff1d\uff1d\uff1d\uff1d\uff1d\uff1d\uff1d\uff1d\uff1d\uff1d\uff1d\uff1d\uff1d\n\n[Viewer Rules]\nThank you for watching my stream!\nTo help everyone enjoy the stream more, please follow these rules:\n1.Be nice to other viewers. Don\u2019t spam or troll \n2.If you see spam or trolling, don\u2019t respond. Just block, report, and ignore those comments.\n3.Talk about the stream, but please don\u2019t bring up unrelated topics or have personal conversations.\n4.Don\u2019t bring up other streamers or streams unless I mention them.\n5.Similarly, don\u2019t talk about me or my stream in other streamers\u2019 chat.\n6.Chatting before the stream starts is fine as long as it's not completely unrelated to Takanashi Kiara.\n7. Backseating is welcome in most of my streams unless I say so. No spoilers!\n\n\uff1d\uff1d\uff1d\uff1d\uff1d\uff1d\uff1d\uff1d\uff1d\uff1d\uff1d\uff1d\uff1d\uff1d\uff1d\uff1d\uff1d\uff1d\uff1d\uff1d\uff1d\uff1d\uff1d\uff1d\uff1d\n\n\nopening animation by @Dakuma_Art\nEnding screen by @akira0053 and @grape.daze\nending music by umiboshi (youtube)\n\n\uff1d\uff1d\uff1d\uff1d\uff1d\uff1d\uff1d\uff1d\uff1d\uff1d\uff1d\uff1d\uff1d\uff1d\uff1d\uff1d\uff1d\uff1d\uff1d\uff1d\uff1d\uff1d\uff1d\uff1d\uff1d\n\n[Fan Work Guidelines]\nhttps://en.hololive.tv/terms\n\n\uff1d\uff1d\uff1d\uff1d\uff1d\uff1d\uff1d\uff1d\uff1d\uff1d\uff1d\uff1d\uff1d\uff1d\uff1d\uff1d\uff1d\uff1d\uff1d\uff1d\uff1d\uff1d\uff1d\uff1d\uff1d\n\n[Official Online Shop]\nhttps://hololive.booth.pm/\n\n[Holoschedule] (Check all members streaming schedules)\nhttps://schedule.hololive.tv/#hololive\n\n\uff1d\uff1d\uff1d\uff1d\uff1d\uff1d\uff1d\uff1d\uff1d\uff1d\uff1d\uff1d\uff1d\uff1d\uff1d\uff1d\uff1d\uff1d\uff1d\uff1d\uff1d\uff1d\uff1d\uff1d\uff1d\n\n[Hololive Production]\n\u30fbHololive English YouTube Channel: https://t.co/LcYDgFF9V0?amp=1\n\u30fbHololive Production Official Twitter: https://twitter.com/hololivetv\n\u30fbHololive English Official Twitter: https://twitter.com/hololive_En\n\u30fbHololive English Official Reddit: https://www.reddit.com/r/Hololive/\n\n\uff1d\uff1d\uff1d\uff1d\uff1d\uff1d\uff1d\uff1d\uff1d\uff1d\uff1d\uff1d\uff1d\uff1d\uff1d\uff1d\uff1d\uff1d\uff1d\uff1d\uff1d\uff1d\uff1d\uff1d\uff1d", "display_id": "ZpvSy8pffOs", "downloader_options": {"http_chunk_size": 10485760}, "duration": 18143, "duration_string": "5:02:23", "epoch": 1733761544, "ext": "m4a", "extractor": "youtube", "extractor_key": "Youtube", "filesize": 293625790, "filesize_approx": 293624837, "format": "140 - audio only (medium)", "format_id": "140", "format_note": "medium", "fulltitle": "\u3010MEMBERS ONLY\u3011play gaem!!!!!!! STS or smth else!!!!!!!!", "has_drm": false, "http_headers": {"Accept": "text/html,application/xhtml+xml,application/xml;q=0.9,*/*;q=0.8", "Accept-Language": "en-us,en;q=0.5", "Sec-Fetch-Mode": "navigate", "User-Agent": "Mozilla/5.0 (Windows NT 10.0; Win64; x64) AppleWebKit/537.36 (KHTML, like Gecko) Chrome/92.0.4515.107 Safari/537.36"}, "id": "ZpvSy8pffOs", "is_live": false, "language": "en", "language_preference": -1, "like_count": 1061, "live_status": "was_live", "playable_in_embed": true, "protocol": "https", "quality": 3.0, "release_date": "20230323", "release_timestamp": 1679599952, "release_year": 2023, "resolution": "audio only", "source_preference": -1, "tags": ["\u30db\u30ed\u30e9\u30a4\u30d6", "hololive", "\u30db\u30ed\u30e9\u30a4\u30d6\u30d7\u30ed\u30c0\u30af\u30b7\u30e7\u30f3", "hololive production", "\u30db\u30ed\u30d7\u30ed", "Takanashi", "Kiara", "\u5c0f\u9ce5\u904a", "\u30ad\u30a2\u30e9", "hololive English", "holoEN", "hololive Myth", "holoMyth"], "tbr": 129.471, "thumbnail": "https://i.ytimg.com/vi/ZpvSy8pffOs/maxresdefault.jpg", "timestamp": 1679580842, "title": "\u3010MEMBERS ONLY\u3011play gaem!!!!!!! STS or smth else!!!!!!!!", "upload_date": "20230323", "uploader": "Takanashi Kiara Ch. hololive-EN", "uploader_id": "@TakanashiKiara", "uploader_url": "https://www.youtube.com/@TakanashiKiara", "url": "https://rr5---sn-2gb7sn7y.googlevideo.com/videoplayback?expire=1733783143&ei=BxpXZ4yjFL7e6dsPps-M-QM&ip=78.80.167.40&id=o-ABoN5-5srwm2pZpKzTfRojS3qce8hbmiFXiOZ4IKnAcp&itag=140&source=youtube&requiressl=yes&xpc=EgVo2aDSNQ%3D%3D&met=1733761543%2C&mh=oU&mm=31%2C29&mn=sn-2gb7sn7y%2Csn-2gb7snez&ms=au%2Crdu&mv=m&mvi=5&pl=19&rms=au%2Cau&initcwndbps=1438750&siu=1&bui=AQn3pFSR7LAvGX4Mr7pXzm16t8qCkgETLphnlQINGtky0RluzWFzGAY05fAhQUx7UKfX2UGuVg&spc=qtApAX0z5fAGFzi58_6JRn5K58FW0doe2TkxI-W15gxkfz2vClaLFtsO7IwEAhnPyQ&vprv=1&svpuc=1&mime=audio%2Fmp4&ns=4n-WbILiVLuOSVov6tjSN5IQ&rqh=1&gir=yes&clen=293625790&dur=18143.049&lmt=1679619271893690&mt=1733761307&fvip=4&keepalive=yes&fexp=51326932%2C51335594%2C51347746&c=WEB_CREATOR&sefc=1&txp=7318224&n=fRlbLtt1aElByQ&sparams=expire%2Cei%2Cip%2Cid%2Citag%2Csource%2Crequiressl%2Cxpc%2Csiu%2Cbui%2Cspc%2Cvprv%2Csvpuc%2Cmime%2Cns%2Crqh%2Cgir%2Cclen%2Cdur%2Clmt&lsparams=met%2Cmh%2Cmm%2Cmn%2Cms%2Cmv%2Cmvi%2Cpl%2Crms%2Cinitcwndbps&lsig=AGluJ3MwRgIhAMBNiU6ESk_e9M2-whEoJPy4cLtYOr1_Dks2dCmTRue-AiEAsJMKbYXTh8pnzlkLZIi9SZTrsmRqq7Nnnq_5FSAPmRc%3D&sig=AJfQdSswRQIgRmhK1L6Fb_zG6EENyIPLQfpbj4LRu73jDAIBH2fNYgICIQC4NnfRQtD8aetPSIEhUQ8P2kMhwiLyRuTwNjH_T6SGsA%3D%3D", "vbr": 0, "vcodec": "none", "video_ext": "none", "view_count": 6870, "was_live": true, "webpage_url": "https://www.youtube.com/watch?v=ZpvSy8pffOs", "webpage_url_basename": "watch", "webpage_url_domain": "youtube.com"}