{"_format_sort_fields": ["quality", "res", "fps", "hdr:12", "source", "vcodec", "channels", "acodec", "lang", "proto"], "_type": "video", "_version": {"release_git_head": "197d0b03b6a3c8fe4fa5ace630eeffec629bf72c", "repository": "yt-dlp/yt-dlp", "version": "2024.11.04"}, "abr": 121.152, "acodec": "opus", "age_limit": 0, "aspect_ratio": 1.78, "asr": 48000, "audio_channels": 2, "availability": "public", "categories": ["Entertainment"], "channel": "Mori Calliope Ch. hololive-EN", "channel_follower_count": 2470000, "channel_id": "UCL_qhgtOy0dy1Agp8vkySQg", "channel_is_verified": true, "channel_url": "https://www.youtube.com/channel/UCL_qhgtOy0dy1Agp8vkySQg", "comment_count": 127, "description": "with @TakanashiKiara \n\n2023 May 3rd Mori Calliope Major Debut Concert \"New Underworld Order\" Blu-ray release!!\n\u203bLimited edition includes a tapestry \nhttps://lnk.to/MC_NUO\n\nthumb: https://twitter.com/CrManzana/status/1628434865946337280?s=20\n\n--------------------------------\nRequest from hololive Production to underage viewers:\nPlease be sure to check the link below before viewing our content.\nhttps://en.hololive.tv/request-to-minors\n--------------------------------", "display_id": "8W-Tmvs6szA", "duration": 6247, "duration_string": "1:44:07", "dynamic_range": "SDR", "epoch": 1732751823, "ext": "mkv", "extractor": "youtube", "extractor_key": "Youtube", "filesize_approx": 1910976201, "format": "137 - 1920x1080 (1080p)+251 - audio only (medium)", "format_id": "137+251", "format_note": "1080p+medium", "fps": 30, "fulltitle": "\u3010OFF COLLAB\u3011Rubix Cube and Chill...with Takanashi Kiara!", "height": 1080, "id": "8W-Tmvs6szA", "is_live": false, "language": "en", "like_count": 12978, "live_status": "was_live", "playable_in_embed": true, "protocol": "https+https", "release_date": "20230302", "release_timestamp": 1677762022, "release_year": 2023, "resolution": "1920x1080", "tags": ["\u30db\u30ed\u30e9\u30a4\u30d6", "hololive", "\u30db\u30ed\u30e9\u30a4\u30d6\u30d7\u30ed\u30c0\u30af\u30b7\u30e7\u30f3", "hololive production", "\u30db\u30ed\u30d7\u30ed", "Mori", "Calliope", "\u30ab\u30ea\u30aa\u30da", "hololive English", "holoEN", "hololive Myth", "holoMyth"], "tbr": 2447.197, "thumbnail": "https://i.ytimg.com/vi/8W-Tmvs6szA/maxresdefault.jpg", "timestamp": 1677770089, "title": "\u3010OFF COLLAB\u3011Rubix Cube and Chill...with Takanashi Kiara!", "upload_date": "20230302", "uploader": "Mori Calliope Ch. hololive-EN", "uploader_id": "@MoriCalliope", "uploader_url": "https://www.youtube.com/@MoriCalliope", "vbr": 2326.045, "vcodec": "avc1.640028", "view_count": 150755, "was_live": true, "webpage_url": "https://www.youtube.com/watch?v=8W-Tmvs6szA", "webpage_url_basename": "watch", "webpage_url_domain": "youtube.com", "width": 1920}