{"available_at": "2024-04-01T00:37:18.000Z", "channel": {"english_name": "Takanashi Kiara", "id": "UCHsx4Hqa-1ORjQTh9TYDhww", "name": "Takanashi Kiara Ch. hololive-EN", "org": "Hololive", "photo": "https://yt3.ggpht.com/w7TKJYU7zmamFmf-WxfahCo_K7Bg2__Pk-CCBNnbewMG-77OZLqJO9MLvDAmH9nEkZH8OkWgSQ=s800-c-k-c0x00ffffff-no-rj", "suborg": "h English -Myth-", "type": "vtuber"}, "description": "MV & STREAMING PLATFORM RELEASE 6TH OF APRIL 2024\n\uff14\u6708\uff16\u65e5\u306bMV\u3068\u914d\u4fe1\u30b5\u30fc\u30d3\u30b9\u306b\u30ea\u30ea\u30fc\u30b9\u3057\u307e\u3059\uff01\uff01\n\n\n \ud83c\udff5\ufe0f[Twitter] \ud83c\udff5\ufe0f\nhttps://twitter.com/takanashikiara\n\n\n\n \ud83c\udff5\ufe0f[Hashtags] \ud83c\udff5\ufe0f\n#kfp #\u30ad\u30a2\u30e9\u30a4\u30d6#hololiveenglish #holomyth #takanashikiara \nFANART #kfpicasso \n\n\n\n[Fan Work Guidelines]\nhttps://en.hololive.tv/terms\n\n\n\uff1d\uff1d\uff1d\uff1d\uff1d\uff1d\uff1d\uff1d\uff1d\uff1d\uff1d\uff1d\uff1d\uff1d\uff1d\uff1d\uff1d\uff1d\uff1d\uff1d\uff1d\uff1d\uff1d\uff1d\uff1d\n\n\n[Official Online Shop]\nhttps://hololive.booth.pm\n\n\n[Holoschedule] (Check all members streaming schedules)\nhttps://schedule.hololive.tv/#hololive\n\n\n\uff1d\uff1d\uff1d\uff1d\uff1d\uff1d\uff1d\uff1d\uff1d\uff1d\uff1d\uff1d\uff1d\uff1d\uff1d\uff1d\uff1d\uff1d\uff1d\uff1d\uff1d\uff1d\uff1d\uff1d\uff1d\n\n\n\n[Hololive Production]\n\u30fbHololive English YouTube Channel: https://t.co/LcYDgFF9V0?amp=1\n\u30fbHololive Production Official Twitter: https://twitter.com/hololivetv\n\u30fbHololive English Official Twitter: https://twitter.com/hololive_En\n\u30fbHololive English Official Reddit: https://www.reddit.com/r/Hololive/\n\n\n\n\uff1d\uff1d\uff1d\uff1d\uff1d\uff1d\uff1d\uff1d\uff1d\uff1d\uff1d\uff1d\uff1d\uff1d\uff1d\uff1d\uff1d\uff1d\uff1d\uff1d\uff1d\uff1d\uff1d\uff1d\uff1d\n\n\n--------------------------------\nRequest from hololive Production to underage viewers:\nPlease be sure to check the link below before viewing our content.\nhttps://en.hololive.tv/request-to-minors\n--------------------------------", "duration": 25, "id": "uhA9GDclleI", "published_at": "2024-04-01T00:37:18.000Z", "status": "past", "title": "CHIMERA - Takanashi Kiara  \u3010 3D MV Teaser\u3011", "topic_id": "Teaser", "type": "stream"}